[1,["ecpdLyjvZBwrvm+cedCcQy","a1VfbnMSNKeb9tVed7Nc+P","abx4mrQgxISIlxeB74pky9","ffHEta8KBGopvMvD4+skpW","28WDoBBpJFJLKbtdhcPIfV","a2MjXRFdtLlYQ5ouAFv/+R","d7YJhseclK6ZCTPeEoEyaU","7bOq/mRqVErb+5ae55GhZP","d2RqthMYBFa6GrXCNQF+e5","c3GNnGTaRBKqlfzw6sagsE","aanmOwZwRNJ6HU/UkW7UOp","deM095J2lMiIeWKUDnfnqv","9dWghpB29FHL/ii4EXkZf9","61Z3XoQdJHVIHZ9z7H2g1l","45BVU3pctJJaUPW6LSJD0L","70/8lBZ55GoLqbA5XZBo2N","87YEXxVBVFGLH86v2YhTaI","a2Gt0LWepPAZagywPOE9Xh","b6nJ+YGyZFqa1O2wK/Icp2","caohotOUBLl7oTfKVm4tMU","47xpp0BIVLuZNu3qr43lZc","61iP4rMfdFL7T51PFv9ycL","cbIQ1E1wBHRZBFL+Lrtszj","72oFLn6M9CbKDPau57bWEe","b7PCW0oeNCJILBtS3zNGlZ","cd00hJ2jlPaZZsLrvKOzy7","c2m2tXx15OL7e4bnpgTbUx","a2Vt2sQopGBIDYL6zs/oUE","eaOMmvLWBPZo3uGSMRO2Ih","ceAdz4UlpP1bVnMUY57I9F","93u+2T7WlIKYb81/R1dgb8","d7A8pIGR1DTKb2tGAky0JM","8cI0s6Jp9H3b1AN4noGtM2","42VX6gX6JLhpDBa9YABxyM","40NEdW3hBAQ4dRbWfsvVW+","16G8Ff8m9P+YuI6ZPSuNi2","edSn2mjhJALqQnOq6ie05H","6bwH5s7sxH4YmuYKWjDYF7","0aV78nO8tHdLeFTxhWxaUt","b3ml1eMCNLvrjMRkPRt9Ny","ed5CPstWpBwLJt+riSkB0A","02delMVqdBD70a/HSD99FK","00F79EwCJLcYuDtZkc1SL1"],["node","_spriteFrame","_textureSetter","_parent","talknode","herolich","controlbalck","heroend","scene","dialogbox","_defaultClip","_clip"],[["cc.Node",["_name","_active","_id","_objFlags","_components","_parent","_contentSize","_trs","_children","_color","_eulerAngles"],-1,9,1,5,7,2,5,5],"cc.SpriteFrame",["cc.ParticleSystem",["_custom","totalParticles","emissionRate","lifeVar","angle","startSize","startSizeVar","endSize","endSizeVar","startSpin","endSpin","endSpinVar","_positionType","speed","speedVar","tangentialAccel","tangentialAccelVar","radialAccel","radialAccelVar","life","_dstBlendFactor","angleVar","node","_materials","_startColor","_startColorVar","_endColor","_endColorVar","posVar","gravity","_spriteFrame"],-19,1,3,8,8,8,8,5,5,6],["cc.AnimationClip",["_name","_duration","curveData","events","sample"],-2],["cc.Sprite",["node","_materials","_spriteFrame"],3,1,3,6],["cc.SceneAsset",["_name","asyncLoadAssets"],1],["cc.Node",["_name","_parent","_components","_contentSize","_trs"],2,1,12,5,7],["cc.Node",["_name","_active","_parent","_components","_contentSize","_trs"],1,1,2,5,7],["cc.Mask",["node","_materials"],3,1,3],["532091JKp9L54OVHqVEn6kv",["node","heroend","controlbalck","herolich","talknode","dialogbox"],3,1,1,1,1,1,6],["cc.Animation",["node","_clips","_defaultClip"],3,1,3,6],["cc.AudioSource",["_volume","_loop","playOnLoad","preload","node","_clip"],-1,1,6],["cc.Canvas",["_fitWidth","_fitHeight","node","_designResolution"],1,1,5],["cc.Widget",["_alignFlags","node"],2,1],["cc.Camera",["_clearFlags","_depth","node","_backgroundColor"],1,1,5],["79cb5TUxZFB4Z1fC9DUzjp3",["node"],3,1],["cc.Scene",["_name","_children","_anchorPoint","_trs"],2,2,5,7]],[[4,0,1,2,1],[0,0,1,5,4,6,7,3],[0,0,5,4,6,7,2],[3,0,1,4,3,2,6],[0,0,1,5,8,4,6,3],[0,0,5,4,6,2],[0,0,5,4,7,10,2],[8,0,1,1],[4,0,1,1],[3,0,1,2,4],[3,0,1,3,2,5],[5,0,1,3],[0,0,1,8,4,6,3],[0,0,8,4,9,2],[0,0,2,8,4,6,7,3],[0,0,3,5,8,4,9,6,3],[0,0,5,8,4,6,7,2],[0,0,1,5,3],[0,0,1,5,4,9,6,7,3],[0,0,1,5,4,7,10,3],[0,0,1,5,4,7,3],[0,0,5,8,2],[0,0,5,7,2],[6,0,1,2,3,4,2],[7,0,1,2,3,4,5,3],[9,0,1,2,3,4,5,1],[10,0,1,2,1],[11,0,1,2,3,4,5,5],[12,0,1,2,3,3],[13,0,1,2],[14,0,1,2,3,3],[15,0,1],[16,0,1,2,3,2],[2,20,0,1,2,19,3,4,5,6,7,8,9,10,11,12,13,14,15,16,17,18,22,23,24,25,26,27,28,29,30,22],[2,0,1,2,19,3,4,21,5,6,7,8,9,10,11,12,13,14,15,16,17,18,22,23,24,25,26,27,28,29,30,22],[2,0,1,2,19,3,4,5,6,7,8,9,10,11,12,13,14,15,16,17,18,22,23,24,25,26,27,28,29,30,21],[2,20,0,1,2,3,4,21,5,6,7,8,9,10,11,12,13,14,15,16,17,18,22,23,24,25,26,27,28,29,30,22]],[[[{"name":"richCopy","rect":[0,0,31,32],"offset":[-0.5,0],"originalSize":[32,32],"capInsets":[0,0,0,0]}],[1],0,[0],[2],[3]],[[[3,"badend2",31.333333333333332,30,[{"frame":5.066666666666666,"func":"finaltalkTwo","params":[]}],{"paths":{"end3Cbackground":{"props":{"active":[{"frame":0,"value":false},{"frame":0.03333333333333333,"value":true}],"opacity":[{"frame":0,"value":0},{"frame":0.8,"value":254}]}},"end3Cbackground/handjoit":{"props":{"position":[{"frame":0.4666666666666667,"value":[0,-108.126,0]},{"frame":3.8,"value":[0,19.462,0]}]}},"end3Cbackground/handjoit/boym5_hand":{"props":{"position":[{"frame":0.4666666666666667,"value":[-2.95,-146.4]},{"frame":0.5,"value":[-3.5,-145.72]},{"frame":0.5333333333333333,"value":[-6.49,-146.18]},{"frame":0.5666666666666667,"value":[-5.89,-144.88]},{"frame":0.6,"value":[-7.03,-146.45]},{"frame":0.6333333333333333,"value":[-4.84,-147.08]},{"frame":0.6666666666666666,"value":[-4.04,-144.93]},{"frame":0.7,"value":[-3.83,-146.96]},{"frame":0.7333333333333333,"value":[-6.49,-146.18]},{"frame":0.7666666666666667,"value":[-4.5,-145.42]},{"frame":0.8,"value":[-5.92,-146.95]},{"frame":1,"value":[-2.95,-146.4]},{"frame":1.0333333333333334,"value":[-3.5,-145.72]},{"frame":1.0666666666666667,"value":[-6.49,-146.18]},{"frame":1.1,"value":[-5.89,-144.88]},{"frame":1.1333333333333333,"value":[-7.03,-146.45]},{"frame":1.1666666666666667,"value":[-4.84,-147.08]},{"frame":1.2,"value":[-4.04,-144.93]},{"frame":1.2333333333333334,"value":[-3.83,-146.96]},{"frame":1.2666666666666666,"value":[-6.49,-146.18]},{"frame":1.3,"value":[-4.5,-145.42]},{"frame":1.3333333333333333,"value":[-5.92,-146.95]},{"frame":1.5333333333333334,"value":[-2.95,-146.4],"motionPath":[]},{"frame":1.5666666666666667,"value":[-3.5,-145.72],"motionPath":[]},{"frame":1.6,"value":[-6.49,-146.18],"motionPath":[]},{"frame":1.6333333333333333,"value":[-5.89,-144.88],"motionPath":[]},{"frame":1.6666666666666667,"value":[-7.03,-146.45],"motionPath":[]},{"frame":1.7,"value":[-4.84,-147.08],"motionPath":[]},{"frame":1.7333333333333334,"value":[-4.04,-144.93],"motionPath":[]},{"frame":1.7666666666666666,"value":[-3.83,-146.96],"motionPath":[]},{"frame":1.8,"value":[-6.49,-146.18],"motionPath":[]},{"frame":1.8333333333333333,"value":[-4.5,-145.42],"motionPath":[]},{"frame":1.8666666666666667,"value":[-5.92,-146.95],"motionPath":[]},{"frame":2,"value":[-2.95,-146.4]},{"frame":2.033333333333333,"value":[-3.5,-145.72]},{"frame":2.066666666666667,"value":[-6.49,-146.18]},{"frame":2.1,"value":[-5.89,-144.88]},{"frame":2.1333333333333333,"value":[-7.03,-146.45]},{"frame":2.1666666666666665,"value":[-4.84,-147.08]},{"frame":2.2,"value":[-4.04,-144.93]},{"frame":2.2333333333333334,"value":[-3.83,-146.96]},{"frame":2.2666666666666666,"value":[-6.49,-146.18]},{"frame":2.3,"value":[-4.5,-145.42]},{"frame":2.3333333333333335,"value":[-5.92,-146.95]},{"frame":2.5,"value":[-2.95,-146.4]},{"frame":2.533333333333333,"value":[-3.5,-145.72]},{"frame":2.566666666666667,"value":[-6.49,-146.18]},{"frame":2.6,"value":[-5.89,-144.88]},{"frame":2.6333333333333333,"value":[-7.03,-146.45]},{"frame":2.6666666666666665,"value":[-4.84,-147.08]},{"frame":2.7,"value":[-4.04,-144.93]},{"frame":2.7333333333333334,"value":[-3.83,-146.96]},{"frame":2.7666666666666666,"value":[-6.49,-146.18]},{"frame":2.8,"value":[-4.5,-145.42]},{"frame":2.8333333333333335,"value":[-5.92,-146.95]},{"frame":3.033333333333333,"value":[-2.95,-146.4]},{"frame":3.066666666666667,"value":[-3.5,-145.72]},{"frame":3.1,"value":[-6.49,-146.18]},{"frame":3.1333333333333333,"value":[-5.89,-144.88]},{"frame":3.1666666666666665,"value":[-7.03,-146.45]},{"frame":3.2,"value":[-4.84,-147.08]},{"frame":3.2333333333333334,"value":[-4.04,-144.93]},{"frame":3.2666666666666666,"value":[-3.83,-146.96]},{"frame":3.3,"value":[-6.49,-146.18]},{"frame":3.3333333333333335,"value":[-4.5,-145.42]},{"frame":3.3666666666666667,"value":[-5.92,-146.95]},{"frame":3.566666666666667,"value":[-2.95,-146.4]},{"frame":3.6,"value":[-3.5,-145.72]},{"frame":3.6333333333333333,"value":[-6.49,-146.18]},{"frame":3.6666666666666665,"value":[-5.89,-144.88]},{"frame":3.7,"value":[-7.03,-146.45]},{"frame":3.7333333333333334,"value":[-4.84,-147.08]},{"frame":3.7666666666666666,"value":[-4.04,-144.93]},{"frame":3.8,"value":[-3.83,-146.96]},{"frame":3.8333333333333335,"value":[-6.49,-146.18]},{"frame":3.8666666666666667,"value":[-4.5,-145.42]},{"frame":3.9,"value":[-5.92,-146.95]},{"frame":4.033333333333333,"value":[-2.95,-146.4]},{"frame":4.066666666666666,"value":[-3.5,-145.72]},{"frame":4.1,"value":[-6.49,-146.18]},{"frame":4.133333333333334,"value":[-5.89,-144.88]},{"frame":4.166666666666667,"value":[-7.03,-146.45]},{"frame":4.2,"value":[-4.84,-147.08]},{"frame":4.233333333333333,"value":[-4.04,-144.93]},{"frame":4.266666666666667,"value":[-3.83,-146.96]},{"frame":4.3,"value":[-6.49,-146.18]},{"frame":4.333333333333333,"value":[-4.5,-145.42]},{"frame":4.366666666666666,"value":[-5.92,-146.95]},{"frame":4.5,"value":[-2.95,-146.4]},{"frame":4.533333333333333,"value":[-3.5,-145.72]},{"frame":4.566666666666666,"value":[-6.49,-146.18]},{"frame":4.6,"value":[-5.89,-144.88]},{"frame":4.633333333333334,"value":[-7.03,-146.45]},{"frame":4.666666666666667,"value":[-4.84,-147.08]},{"frame":4.7,"value":[-4.04,-144.93]},{"frame":4.733333333333333,"value":[-3.83,-146.96]},{"frame":4.766666666666667,"value":[-6.49,-146.18]},{"frame":4.8,"value":[-4.5,-145.42]},{"frame":4.833333333333333,"value":[-5.92,-146.95]},{"frame":5.033333333333333,"value":[-2.95,-146.4]},{"frame":5.066666666666666,"value":[-3.5,-145.72]},{"frame":5.1,"value":[-6.49,-146.18]},{"frame":5.133333333333334,"value":[-5.89,-144.88]},{"frame":5.166666666666667,"value":[-7.03,-146.45]},{"frame":5.2,"value":[-4.84,-147.08]},{"frame":5.233333333333333,"value":[-4.04,-144.93]},{"frame":5.266666666666667,"value":[-3.83,-146.96]},{"frame":5.3,"value":[-6.49,-146.18]},{"frame":5.333333333333333,"value":[-4.5,-145.42]},{"frame":5.366666666666666,"value":[-5.92,-146.95]},{"frame":5.566666666666666,"value":[-2.95,-146.4]},{"frame":5.6,"value":[-3.5,-145.72]},{"frame":5.633333333333334,"value":[-6.49,-146.18]},{"frame":5.666666666666667,"value":[-5.89,-144.88]},{"frame":5.7,"value":[-7.03,-146.45]},{"frame":5.733333333333333,"value":[-4.84,-147.08]},{"frame":5.766666666666667,"value":[-4.04,-144.93]},{"frame":5.8,"value":[-3.83,-146.96]},{"frame":5.833333333333333,"value":[-6.49,-146.18]},{"frame":5.866666666666666,"value":[-4.5,-145.42]},{"frame":5.9,"value":[-5.92,-146.95]},{"frame":6.033333333333333,"value":[-2.95,-146.4]},{"frame":6.066666666666666,"value":[-3.5,-145.72]},{"frame":6.1,"value":[-6.49,-146.18]},{"frame":6.133333333333334,"value":[-5.89,-144.88]},{"frame":6.166666666666667,"value":[-7.03,-146.45]},{"frame":6.2,"value":[-4.84,-147.08]},{"frame":6.233333333333333,"value":[-4.04,-144.93]},{"frame":6.266666666666667,"value":[-3.83,-146.96]},{"frame":6.3,"value":[-6.49,-146.18]},{"frame":6.333333333333333,"value":[-4.5,-145.42]},{"frame":6.366666666666666,"value":[-5.92,-146.95]},{"frame":6.566666666666666,"value":[-2.95,-146.4]},{"frame":6.6,"value":[-3.5,-145.72]},{"frame":6.633333333333334,"value":[-6.49,-146.18]},{"frame":6.666666666666667,"value":[-5.89,-144.88]},{"frame":6.7,"value":[-7.03,-146.45]},{"frame":6.733333333333333,"value":[-4.84,-147.08]},{"frame":6.766666666666667,"value":[-4.04,-144.93]},{"frame":6.8,"value":[-3.83,-146.96]},{"frame":6.833333333333333,"value":[-6.49,-146.18]},{"frame":6.866666666666666,"value":[-4.5,-145.42]},{"frame":6.9,"value":[-5.92,-146.95]},{"frame":7.1,"value":[-2.95,-146.4]},{"frame":7.133333333333334,"value":[-3.5,-145.72]},{"frame":7.166666666666667,"value":[-6.49,-146.18]},{"frame":7.2,"value":[-5.89,-144.88]},{"frame":7.233333333333333,"value":[-7.03,-146.45]},{"frame":7.266666666666667,"value":[-4.84,-147.08]},{"frame":7.3,"value":[-4.04,-144.93]},{"frame":7.333333333333333,"value":[-3.83,-146.96]},{"frame":7.366666666666666,"value":[-6.49,-146.18]},{"frame":7.4,"value":[-4.5,-145.42]},{"frame":7.433333333333334,"value":[-5.92,-146.95]},{"frame":7.633333333333334,"value":[-2.95,-146.4]},{"frame":7.666666666666667,"value":[-3.5,-145.72]},{"frame":7.7,"value":[-6.49,-146.18]},{"frame":7.733333333333333,"value":[-5.89,-144.88]},{"frame":7.766666666666667,"value":[-7.03,-146.45]},{"frame":7.8,"value":[-4.84,-147.08]},{"frame":7.833333333333333,"value":[-4.04,-144.93]},{"frame":7.866666666666666,"value":[-3.83,-146.96]},{"frame":7.9,"value":[-6.49,-146.18]},{"frame":7.933333333333334,"value":[-4.5,-145.42]},{"frame":7.966666666666667,"value":[-5.92,-146.95]},{"frame":8.1,"value":[-2.95,-146.4]},{"frame":8.133333333333333,"value":[-3.5,-145.72]},{"frame":8.166666666666666,"value":[-6.49,-146.18]},{"frame":8.2,"value":[-5.89,-144.88]},{"frame":8.233333333333333,"value":[-7.03,-146.45]},{"frame":8.266666666666667,"value":[-4.84,-147.08]},{"frame":8.3,"value":[-4.04,-144.93]},{"frame":8.333333333333334,"value":[-3.83,-146.96]},{"frame":8.366666666666667,"value":[-6.49,-146.18]},{"frame":8.4,"value":[-4.5,-145.42]},{"frame":8.433333333333334,"value":[-5.92,-146.95]},{"frame":8.6,"value":[-2.95,-146.4]},{"frame":8.633333333333333,"value":[-3.5,-145.72]},{"frame":8.666666666666666,"value":[-6.49,-146.18]},{"frame":8.7,"value":[-5.89,-144.88]},{"frame":8.733333333333333,"value":[-7.03,-146.45]},{"frame":8.766666666666667,"value":[-4.84,-147.08]},{"frame":8.8,"value":[-4.04,-144.93]},{"frame":8.833333333333334,"value":[-3.83,-146.96]},{"frame":8.866666666666667,"value":[-6.49,-146.18]},{"frame":8.9,"value":[-4.5,-145.42]},{"frame":8.933333333333334,"value":[-5.92,-146.95]},{"frame":9.133333333333333,"value":[-2.95,-146.4]},{"frame":9.166666666666666,"value":[-3.5,-145.72]},{"frame":9.2,"value":[-6.49,-146.18]},{"frame":9.233333333333333,"value":[-5.89,-144.88]},{"frame":9.266666666666667,"value":[-7.03,-146.45]},{"frame":9.3,"value":[-4.84,-147.08]},{"frame":9.333333333333334,"value":[-4.04,-144.93]},{"frame":9.366666666666667,"value":[-3.83,-146.96]},{"frame":9.4,"value":[-6.49,-146.18]},{"frame":9.433333333333334,"value":[-4.5,-145.42]},{"frame":9.466666666666667,"value":[-5.92,-146.95]},{"frame":9.666666666666666,"value":[-2.95,-146.4]},{"frame":9.7,"value":[-3.5,-145.72]},{"frame":9.733333333333333,"value":[-6.49,-146.18]},{"frame":9.766666666666667,"value":[-5.89,-144.88]},{"frame":9.8,"value":[-7.03,-146.45]},{"frame":9.833333333333334,"value":[-4.84,-147.08]},{"frame":9.866666666666667,"value":[-4.04,-144.93]},{"frame":9.9,"value":[-3.83,-146.96]},{"frame":9.933333333333334,"value":[-6.49,-146.18]},{"frame":9.966666666666667,"value":[-4.5,-145.42]},{"frame":10,"value":[-5.92,-146.95]},{"frame":10.133333333333333,"value":[-2.95,-146.4]},{"frame":10.166666666666666,"value":[-3.5,-145.72]},{"frame":10.2,"value":[-6.49,-146.18]},{"frame":10.233333333333333,"value":[-5.89,-144.88]},{"frame":10.266666666666667,"value":[-7.03,-146.45]},{"frame":10.3,"value":[-4.84,-147.08]},{"frame":10.333333333333334,"value":[-4.04,-144.93]},{"frame":10.366666666666667,"value":[-3.83,-146.96]},{"frame":10.4,"value":[-6.49,-146.18]},{"frame":10.433333333333334,"value":[-4.5,-145.42]},{"frame":10.466666666666667,"value":[-5.92,-146.95]},{"frame":10.6,"value":[-2.95,-146.4]},{"frame":10.633333333333333,"value":[-3.5,-145.72]},{"frame":10.666666666666666,"value":[-6.49,-146.18]},{"frame":10.7,"value":[-5.89,-144.88]},{"frame":10.733333333333333,"value":[-7.03,-146.45]},{"frame":10.766666666666667,"value":[-4.84,-147.08]},{"frame":10.8,"value":[-4.04,-144.93]},{"frame":10.833333333333334,"value":[-3.83,-146.96]},{"frame":10.866666666666667,"value":[-6.49,-146.18]},{"frame":10.9,"value":[-4.5,-145.42]},{"frame":10.933333333333334,"value":[-5.92,-146.95]},{"frame":11.133333333333333,"value":[-2.95,-146.4]},{"frame":11.166666666666666,"value":[-3.5,-145.72]},{"frame":11.2,"value":[-6.49,-146.18]},{"frame":11.233333333333333,"value":[-5.89,-144.88]},{"frame":11.266666666666667,"value":[-7.03,-146.45]},{"frame":11.3,"value":[-4.84,-147.08]},{"frame":11.333333333333334,"value":[-4.04,-144.93]},{"frame":11.366666666666667,"value":[-3.83,-146.96]},{"frame":11.4,"value":[-6.49,-146.18]},{"frame":11.433333333333334,"value":[-4.5,-145.42]},{"frame":11.466666666666667,"value":[-5.92,-146.95]},{"frame":11.666666666666666,"value":[-2.95,-146.4]},{"frame":11.7,"value":[-3.5,-145.72]},{"frame":11.733333333333333,"value":[-6.49,-146.18]},{"frame":11.766666666666667,"value":[-5.89,-144.88]},{"frame":11.8,"value":[-7.03,-146.45]},{"frame":11.833333333333334,"value":[-4.84,-147.08]},{"frame":11.866666666666667,"value":[-4.04,-144.93]},{"frame":11.9,"value":[-3.83,-146.96]},{"frame":11.933333333333334,"value":[-6.49,-146.18]},{"frame":11.966666666666667,"value":[-4.5,-145.42]},{"frame":12,"value":[-5.92,-146.95]},{"frame":12.133333333333333,"value":[-2.95,-146.4]},{"frame":12.166666666666666,"value":[-3.5,-145.72]},{"frame":12.2,"value":[-6.49,-146.18]},{"frame":12.233333333333333,"value":[-5.89,-144.88]},{"frame":12.266666666666667,"value":[-7.03,-146.45]},{"frame":12.3,"value":[-4.84,-147.08]},{"frame":12.333333333333334,"value":[-4.04,-144.93]},{"frame":12.366666666666667,"value":[-3.83,-146.96]},{"frame":12.4,"value":[-6.49,-146.18]},{"frame":12.433333333333334,"value":[-4.5,-145.42]},{"frame":12.466666666666667,"value":[-5.92,-146.95]},{"frame":12.6,"value":[-2.95,-146.4]},{"frame":12.633333333333333,"value":[-3.5,-145.72]},{"frame":12.666666666666666,"value":[-6.49,-146.18]},{"frame":12.7,"value":[-5.89,-144.88]},{"frame":12.733333333333333,"value":[-7.03,-146.45]},{"frame":12.766666666666667,"value":[-4.84,-147.08]},{"frame":12.8,"value":[-4.04,-144.93]},{"frame":12.833333333333334,"value":[-3.83,-146.96]},{"frame":12.866666666666667,"value":[-6.49,-146.18]},{"frame":12.9,"value":[-4.5,-145.42]},{"frame":12.933333333333334,"value":[-5.92,-146.95]},{"frame":13.133333333333333,"value":[-2.95,-146.4]},{"frame":13.166666666666666,"value":[-3.5,-145.72]},{"frame":13.2,"value":[-6.49,-146.18]},{"frame":13.233333333333333,"value":[-5.89,-144.88]},{"frame":13.266666666666667,"value":[-7.03,-146.45]},{"frame":13.3,"value":[-4.84,-147.08]},{"frame":13.333333333333334,"value":[-4.04,-144.93]},{"frame":13.366666666666667,"value":[-3.83,-146.96]},{"frame":13.4,"value":[-6.49,-146.18]},{"frame":13.433333333333334,"value":[-4.5,-145.42]},{"frame":13.466666666666667,"value":[-5.92,-146.95]},{"frame":13.666666666666666,"value":[-2.95,-146.4]},{"frame":13.7,"value":[-3.5,-145.72]},{"frame":13.733333333333333,"value":[-6.49,-146.18]},{"frame":13.766666666666667,"value":[-5.89,-144.88]},{"frame":13.8,"value":[-7.03,-146.45]},{"frame":13.833333333333334,"value":[-4.84,-147.08]},{"frame":13.866666666666667,"value":[-4.04,-144.93]},{"frame":13.9,"value":[-3.83,-146.96]},{"frame":13.933333333333334,"value":[-6.49,-146.18]},{"frame":13.966666666666667,"value":[-4.5,-145.42]},{"frame":14,"value":[-5.92,-146.95]},{"frame":14.133333333333333,"value":[-2.95,-146.4]},{"frame":14.166666666666666,"value":[-3.5,-145.72]},{"frame":14.2,"value":[-6.49,-146.18]},{"frame":14.233333333333333,"value":[-5.89,-144.88]},{"frame":14.266666666666667,"value":[-7.03,-146.45]},{"frame":14.3,"value":[-4.84,-147.08]},{"frame":14.333333333333334,"value":[-4.04,-144.93]},{"frame":14.366666666666667,"value":[-3.83,-146.96]},{"frame":14.4,"value":[-6.49,-146.18]},{"frame":14.433333333333334,"value":[-4.5,-145.42]},{"frame":14.466666666666667,"value":[-5.92,-146.95]},{"frame":14.633333333333333,"value":[-2.95,-146.4]},{"frame":14.666666666666666,"value":[-3.5,-145.72]},{"frame":14.7,"value":[-6.49,-146.18]},{"frame":14.733333333333333,"value":[-5.89,-144.88]},{"frame":14.766666666666667,"value":[-7.03,-146.45]},{"frame":14.8,"value":[-4.84,-147.08]},{"frame":14.833333333333334,"value":[-4.04,-144.93]},{"frame":14.866666666666667,"value":[-3.83,-146.96]},{"frame":14.9,"value":[-6.49,-146.18]},{"frame":14.933333333333334,"value":[-4.5,-145.42]},{"frame":14.966666666666667,"value":[-5.92,-146.95]},{"frame":15.166666666666666,"value":[-2.95,-146.4]},{"frame":15.2,"value":[-3.5,-145.72]},{"frame":15.233333333333333,"value":[-6.49,-146.18]},{"frame":15.266666666666667,"value":[-5.89,-144.88]},{"frame":15.3,"value":[-7.03,-146.45]},{"frame":15.333333333333334,"value":[-4.84,-147.08]},{"frame":15.366666666666667,"value":[-4.04,-144.93]},{"frame":15.4,"value":[-3.83,-146.96]},{"frame":15.433333333333334,"value":[-6.49,-146.18]},{"frame":15.466666666666667,"value":[-4.5,-145.42]},{"frame":15.5,"value":[-5.92,-146.95]},{"frame":15.7,"value":[-2.95,-146.4]},{"frame":15.733333333333333,"value":[-3.5,-145.72]},{"frame":15.766666666666667,"value":[-6.49,-146.18]},{"frame":15.8,"value":[-5.89,-144.88]},{"frame":15.833333333333334,"value":[-7.03,-146.45]},{"frame":15.866666666666667,"value":[-4.84,-147.08]},{"frame":15.9,"value":[-4.04,-144.93]},{"frame":15.933333333333334,"value":[-3.83,-146.96]},{"frame":15.966666666666667,"value":[-6.49,-146.18]},{"frame":16,"value":[-4.5,-145.42]},{"frame":16.033333333333335,"value":[-5.92,-146.95]},{"frame":16.166666666666668,"value":[-2.95,-146.4]},{"frame":16.2,"value":[-3.5,-145.72]},{"frame":16.233333333333334,"value":[-6.49,-146.18]},{"frame":16.266666666666666,"value":[-5.89,-144.88]},{"frame":16.3,"value":[-7.03,-146.45]},{"frame":16.333333333333332,"value":[-4.84,-147.08]},{"frame":16.366666666666667,"value":[-4.04,-144.93]},{"frame":16.4,"value":[-3.83,-146.96]},{"frame":16.433333333333334,"value":[-6.49,-146.18]},{"frame":16.466666666666665,"value":[-4.5,-145.42]},{"frame":16.5,"value":[-5.92,-146.95]},{"frame":16.666666666666668,"value":[-4.5,-145.42]},{"frame":16.7,"value":[-5.92,-146.95]},{"frame":16.833333333333332,"value":[-2.95,-146.4]},{"frame":16.866666666666667,"value":[-3.5,-145.72]},{"frame":16.9,"value":[-6.49,-146.18]},{"frame":16.933333333333334,"value":[-5.89,-144.88]},{"frame":16.966666666666665,"value":[-7.03,-146.45]},{"frame":17,"value":[-4.84,-147.08]},{"frame":17.033333333333335,"value":[-4.04,-144.93]},{"frame":17.066666666666666,"value":[-3.83,-146.96]},{"frame":17.1,"value":[-6.49,-146.18]},{"frame":17.133333333333333,"value":[-4.5,-145.42]},{"frame":17.166666666666668,"value":[-5.92,-146.95]},{"frame":17.333333333333332,"value":[-2.95,-146.4]},{"frame":17.366666666666667,"value":[-3.5,-145.72]},{"frame":17.4,"value":[-6.49,-146.18]},{"frame":17.433333333333334,"value":[-5.89,-144.88]},{"frame":17.466666666666665,"value":[-7.03,-146.45]},{"frame":17.5,"value":[-4.84,-147.08]},{"frame":17.533333333333335,"value":[-4.04,-144.93]},{"frame":17.566666666666666,"value":[-3.83,-146.96]},{"frame":17.6,"value":[-6.49,-146.18]},{"frame":17.633333333333333,"value":[-4.5,-145.42]},{"frame":17.666666666666668,"value":[-5.92,-146.95]},{"frame":17.866666666666667,"value":[-2.95,-146.4]},{"frame":17.9,"value":[-3.5,-145.72]},{"frame":17.933333333333334,"value":[-6.49,-146.18]},{"frame":17.966666666666665,"value":[-5.89,-144.88]},{"frame":18,"value":[-7.03,-146.45]},{"frame":18.033333333333335,"value":[-4.84,-147.08]},{"frame":18.066666666666666,"value":[-4.04,-144.93]},{"frame":18.1,"value":[-3.83,-146.96]},{"frame":18.133333333333333,"value":[-6.49,-146.18]},{"frame":18.166666666666668,"value":[-4.5,-145.42]},{"frame":18.2,"value":[-5.92,-146.95]},{"frame":18.4,"value":[-2.95,-146.4]},{"frame":18.433333333333334,"value":[-3.5,-145.72]},{"frame":18.466666666666665,"value":[-6.49,-146.18]},{"frame":18.5,"value":[-5.89,-144.88]},{"frame":18.533333333333335,"value":[-7.03,-146.45]},{"frame":18.566666666666666,"value":[-4.84,-147.08]},{"frame":18.6,"value":[-4.04,-144.93]},{"frame":18.633333333333333,"value":[-3.83,-146.96]},{"frame":18.666666666666668,"value":[-6.49,-146.18]},{"frame":18.7,"value":[-4.5,-145.42]},{"frame":18.733333333333334,"value":[-5.92,-146.95]},{"frame":18.866666666666667,"value":[-2.95,-146.4]},{"frame":18.9,"value":[-3.5,-145.72]},{"frame":18.933333333333334,"value":[-6.49,-146.18]},{"frame":18.966666666666665,"value":[-5.89,-144.88]},{"frame":19,"value":[-7.03,-146.45]},{"frame":19.033333333333335,"value":[-4.84,-147.08]},{"frame":19.066666666666666,"value":[-4.04,-144.93]},{"frame":19.1,"value":[-3.83,-146.96]},{"frame":19.133333333333333,"value":[-6.49,-146.18]},{"frame":19.166666666666668,"value":[-4.5,-145.42]},{"frame":19.2,"value":[-5.92,-146.95]},{"frame":19.333333333333332,"value":[-2.95,-146.4]},{"frame":19.366666666666667,"value":[-3.5,-145.72]},{"frame":19.4,"value":[-6.49,-146.18]},{"frame":19.433333333333334,"value":[-5.89,-144.88]},{"frame":19.466666666666665,"value":[-7.03,-146.45]},{"frame":19.5,"value":[-4.84,-147.08]},{"frame":19.533333333333335,"value":[-4.04,-144.93]},{"frame":19.566666666666666,"value":[-3.83,-146.96]},{"frame":19.6,"value":[-6.49,-146.18]},{"frame":19.633333333333333,"value":[-4.5,-145.42]},{"frame":19.666666666666668,"value":[-5.92,-146.95]},{"frame":19.866666666666667,"value":[-2.95,-146.4]},{"frame":19.9,"value":[-3.5,-145.72]},{"frame":19.933333333333334,"value":[-6.49,-146.18]},{"frame":19.966666666666665,"value":[-5.89,-144.88]},{"frame":20,"value":[-7.03,-146.45]},{"frame":20.033333333333335,"value":[-4.84,-147.08]},{"frame":20.066666666666666,"value":[-4.04,-144.93]},{"frame":20.1,"value":[-3.83,-146.96]},{"frame":20.133333333333333,"value":[-6.49,-146.18]},{"frame":20.166666666666668,"value":[-4.5,-145.42]},{"frame":20.2,"value":[-5.92,-146.95]},{"frame":20.4,"value":[-2.95,-146.4]},{"frame":20.433333333333334,"value":[-3.5,-145.72]},{"frame":20.466666666666665,"value":[-6.49,-146.18]},{"frame":20.5,"value":[-5.89,-144.88]},{"frame":20.533333333333335,"value":[-7.03,-146.45]},{"frame":20.566666666666666,"value":[-4.84,-147.08]},{"frame":20.6,"value":[-4.04,-144.93]},{"frame":20.633333333333333,"value":[-3.83,-146.96]},{"frame":20.666666666666668,"value":[-6.49,-146.18]},{"frame":20.7,"value":[-4.5,-145.42]},{"frame":20.733333333333334,"value":[-5.92,-146.95]},{"frame":20.866666666666667,"value":[-2.95,-146.4]},{"frame":20.9,"value":[-3.5,-145.72]},{"frame":20.933333333333334,"value":[-6.49,-146.18]},{"frame":20.966666666666665,"value":[-5.89,-144.88]},{"frame":21,"value":[-7.03,-146.45]},{"frame":21.033333333333335,"value":[-4.84,-147.08]},{"frame":21.066666666666666,"value":[-4.04,-144.93]},{"frame":21.1,"value":[-3.83,-146.96]},{"frame":21.133333333333333,"value":[-6.49,-146.18]},{"frame":21.166666666666668,"value":[-4.5,-145.42]},{"frame":21.2,"value":[-5.92,-146.95]},{"frame":21.4,"value":[-2.95,-146.4]},{"frame":21.433333333333334,"value":[-3.5,-145.72]},{"frame":21.466666666666665,"value":[-6.49,-146.18]},{"frame":21.5,"value":[-5.89,-144.88]},{"frame":21.533333333333335,"value":[-7.03,-146.45]},{"frame":21.566666666666666,"value":[-4.84,-147.08]},{"frame":21.6,"value":[-4.04,-144.93]},{"frame":21.633333333333333,"value":[-3.83,-146.96]},{"frame":21.666666666666668,"value":[-6.49,-146.18]},{"frame":21.7,"value":[-4.5,-145.42]},{"frame":21.733333333333334,"value":[-5.92,-146.95]},{"frame":21.933333333333334,"value":[-2.95,-146.4]},{"frame":21.966666666666665,"value":[-3.5,-145.72]},{"frame":22,"value":[-6.49,-146.18]},{"frame":22.033333333333335,"value":[-5.89,-144.88]},{"frame":22.066666666666666,"value":[-7.03,-146.45]},{"frame":22.1,"value":[-4.84,-147.08]},{"frame":22.133333333333333,"value":[-4.04,-144.93]},{"frame":22.166666666666668,"value":[-3.83,-146.96]},{"frame":22.2,"value":[-6.49,-146.18]},{"frame":22.233333333333334,"value":[-4.5,-145.42]},{"frame":22.266666666666666,"value":[-5.92,-146.95]},{"frame":22.466666666666665,"value":[-2.95,-146.4]},{"frame":22.5,"value":[-3.5,-145.72]},{"frame":22.533333333333335,"value":[-6.49,-146.18]},{"frame":22.566666666666666,"value":[-5.89,-144.88]},{"frame":22.6,"value":[-7.03,-146.45]},{"frame":22.633333333333333,"value":[-4.84,-147.08]},{"frame":22.666666666666668,"value":[-4.04,-144.93]},{"frame":22.7,"value":[-3.83,-146.96]},{"frame":22.733333333333334,"value":[-6.49,-146.18]},{"frame":22.766666666666666,"value":[-4.5,-145.42]},{"frame":22.8,"value":[-5.92,-146.95]},{"frame":22.933333333333334,"value":[-2.95,-146.4]},{"frame":22.966666666666665,"value":[-3.5,-145.72]},{"frame":23,"value":[-6.49,-146.18]},{"frame":23.033333333333335,"value":[-5.89,-144.88]},{"frame":23.066666666666666,"value":[-7.03,-146.45]},{"frame":23.1,"value":[-4.84,-147.08]},{"frame":23.133333333333333,"value":[-4.04,-144.93]},{"frame":23.166666666666668,"value":[-3.83,-146.96]},{"frame":23.2,"value":[-6.49,-146.18]},{"frame":23.233333333333334,"value":[-4.5,-145.42]},{"frame":23.266666666666666,"value":[-5.92,-146.95]},{"frame":23.433333333333334,"value":[-2.95,-146.4]},{"frame":23.466666666666665,"value":[-3.5,-145.72]},{"frame":23.5,"value":[-6.49,-146.18]},{"frame":23.533333333333335,"value":[-5.89,-144.88]},{"frame":23.566666666666666,"value":[-7.03,-146.45]},{"frame":23.6,"value":[-4.84,-147.08]},{"frame":23.633333333333333,"value":[-4.04,-144.93]},{"frame":23.666666666666668,"value":[-3.83,-146.96]},{"frame":23.7,"value":[-6.49,-146.18]},{"frame":23.733333333333334,"value":[-4.5,-145.42]},{"frame":23.766666666666666,"value":[-5.92,-146.95]},{"frame":23.966666666666665,"value":[-2.95,-146.4]},{"frame":24,"value":[-3.5,-145.72]},{"frame":24.033333333333335,"value":[-6.49,-146.18]},{"frame":24.066666666666666,"value":[-5.89,-144.88]},{"frame":24.1,"value":[-7.03,-146.45]},{"frame":24.133333333333333,"value":[-4.84,-147.08]},{"frame":24.166666666666668,"value":[-4.04,-144.93]},{"frame":24.2,"value":[-3.83,-146.96]},{"frame":24.233333333333334,"value":[-6.49,-146.18]},{"frame":24.266666666666666,"value":[-4.5,-145.42]},{"frame":24.3,"value":[-5.92,-146.95]},{"frame":24.5,"value":[-2.95,-146.4]},{"frame":24.533333333333335,"value":[-3.5,-145.72]},{"frame":24.566666666666666,"value":[-6.49,-146.18]},{"frame":24.6,"value":[-5.89,-144.88]},{"frame":24.633333333333333,"value":[-7.03,-146.45]},{"frame":24.666666666666668,"value":[-4.84,-147.08]},{"frame":24.7,"value":[-4.04,-144.93]},{"frame":24.733333333333334,"value":[-3.83,-146.96]},{"frame":24.766666666666666,"value":[-6.49,-146.18]},{"frame":24.8,"value":[-4.5,-145.42]},{"frame":24.833333333333332,"value":[-5.92,-146.95]},{"frame":24.966666666666665,"value":[-2.95,-146.4]},{"frame":25,"value":[-3.5,-145.72]},{"frame":25.033333333333335,"value":[-6.49,-146.18]},{"frame":25.066666666666666,"value":[-5.89,-144.88]},{"frame":25.1,"value":[-7.03,-146.45]},{"frame":25.133333333333333,"value":[-4.84,-147.08]},{"frame":25.166666666666668,"value":[-4.04,-144.93]},{"frame":25.2,"value":[-3.83,-146.96]},{"frame":25.233333333333334,"value":[-6.49,-146.18]},{"frame":25.266666666666666,"value":[-4.5,-145.42]},{"frame":25.3,"value":[-5.92,-146.95]},{"frame":25.433333333333334,"value":[-2.95,-146.4]},{"frame":25.466666666666665,"value":[-3.5,-145.72]},{"frame":25.5,"value":[-6.49,-146.18]},{"frame":25.533333333333335,"value":[-5.89,-144.88]},{"frame":25.566666666666666,"value":[-7.03,-146.45]},{"frame":25.6,"value":[-4.84,-147.08]},{"frame":25.633333333333333,"value":[-4.04,-144.93]},{"frame":25.666666666666668,"value":[-3.83,-146.96]},{"frame":25.7,"value":[-6.49,-146.18]},{"frame":25.733333333333334,"value":[-4.5,-145.42]},{"frame":25.766666666666666,"value":[-5.92,-146.95]},{"frame":25.966666666666665,"value":[-2.95,-146.4]},{"frame":26,"value":[-3.5,-145.72]},{"frame":26.033333333333335,"value":[-6.49,-146.18]},{"frame":26.066666666666666,"value":[-5.89,-144.88]},{"frame":26.1,"value":[-7.03,-146.45]},{"frame":26.133333333333333,"value":[-4.84,-147.08]},{"frame":26.166666666666668,"value":[-4.04,-144.93]},{"frame":26.2,"value":[-3.83,-146.96]},{"frame":26.233333333333334,"value":[-6.49,-146.18]},{"frame":26.266666666666666,"value":[-4.5,-145.42]},{"frame":26.3,"value":[-5.92,-146.95]},{"frame":26.5,"value":[-2.95,-146.4]},{"frame":26.533333333333335,"value":[-3.5,-145.72]},{"frame":26.566666666666666,"value":[-6.49,-146.18]},{"frame":26.6,"value":[-5.89,-144.88]},{"frame":26.633333333333333,"value":[-7.03,-146.45]},{"frame":26.666666666666668,"value":[-4.84,-147.08]},{"frame":26.7,"value":[-4.04,-144.93]},{"frame":26.733333333333334,"value":[-3.83,-146.96]},{"frame":26.766666666666666,"value":[-6.49,-146.18]},{"frame":26.8,"value":[-4.5,-145.42]},{"frame":26.833333333333332,"value":[-5.92,-146.95]},{"frame":26.966666666666665,"value":[-2.95,-146.4]},{"frame":27,"value":[-3.5,-145.72]},{"frame":27.033333333333335,"value":[-6.49,-146.18]},{"frame":27.066666666666666,"value":[-5.89,-144.88]},{"frame":27.1,"value":[-7.03,-146.45]},{"frame":27.133333333333333,"value":[-4.84,-147.08]},{"frame":27.166666666666668,"value":[-4.04,-144.93]},{"frame":27.2,"value":[-3.83,-146.96]},{"frame":27.233333333333334,"value":[-6.49,-146.18]},{"frame":27.266666666666666,"value":[-4.5,-145.42]},{"frame":27.3,"value":[-5.92,-146.95]},{"frame":27.433333333333334,"value":[-2.95,-146.4]},{"frame":27.466666666666665,"value":[-3.5,-145.72]},{"frame":27.5,"value":[-6.49,-146.18]},{"frame":27.533333333333335,"value":[-5.89,-144.88]},{"frame":27.566666666666666,"value":[-7.03,-146.45]},{"frame":27.6,"value":[-4.84,-147.08]},{"frame":27.633333333333333,"value":[-4.04,-144.93]},{"frame":27.666666666666668,"value":[-3.83,-146.96]},{"frame":27.7,"value":[-6.49,-146.18]},{"frame":27.733333333333334,"value":[-4.5,-145.42]},{"frame":27.766666666666666,"value":[-5.92,-146.95]},{"frame":27.966666666666665,"value":[-2.95,-146.4]},{"frame":28,"value":[-3.5,-145.72]},{"frame":28.033333333333335,"value":[-6.49,-146.18]},{"frame":28.066666666666666,"value":[-5.89,-144.88]},{"frame":28.1,"value":[-7.03,-146.45]},{"frame":28.133333333333333,"value":[-4.84,-147.08]},{"frame":28.166666666666668,"value":[-4.04,-144.93]},{"frame":28.2,"value":[-3.83,-146.96]},{"frame":28.233333333333334,"value":[-6.49,-146.18]},{"frame":28.266666666666666,"value":[-4.5,-145.42]},{"frame":28.3,"value":[-5.92,-146.95]},{"frame":28.5,"value":[-2.95,-146.4]},{"frame":28.533333333333335,"value":[-3.5,-145.72]},{"frame":28.566666666666666,"value":[-6.49,-146.18]},{"frame":28.6,"value":[-5.89,-144.88]},{"frame":28.633333333333333,"value":[-7.03,-146.45]},{"frame":28.666666666666668,"value":[-4.84,-147.08]},{"frame":28.7,"value":[-4.04,-144.93]},{"frame":28.733333333333334,"value":[-3.83,-146.96]},{"frame":28.766666666666666,"value":[-6.49,-146.18]},{"frame":28.8,"value":[-4.5,-145.42]},{"frame":28.833333333333332,"value":[-5.92,-146.95]},{"frame":28.966666666666665,"value":[-2.95,-146.4]},{"frame":29,"value":[-3.5,-145.72]},{"frame":29.033333333333335,"value":[-6.49,-146.18]},{"frame":29.066666666666666,"value":[-5.89,-144.88]},{"frame":29.1,"value":[-7.03,-146.45]},{"frame":29.133333333333333,"value":[-4.84,-147.08]},{"frame":29.166666666666668,"value":[-4.04,-144.93]},{"frame":29.2,"value":[-3.83,-146.96]},{"frame":29.233333333333334,"value":[-6.49,-146.18]},{"frame":29.266666666666666,"value":[-4.5,-145.42]},{"frame":29.3,"value":[-5.92,-146.95]},{"frame":29.466666666666665,"value":[-2.95,-146.4]},{"frame":29.5,"value":[-3.5,-145.72]},{"frame":29.533333333333335,"value":[-6.49,-146.18]},{"frame":29.566666666666666,"value":[-5.89,-144.88]},{"frame":29.6,"value":[-7.03,-146.45]},{"frame":29.633333333333333,"value":[-4.84,-147.08]},{"frame":29.666666666666668,"value":[-4.04,-144.93]},{"frame":29.7,"value":[-3.83,-146.96]},{"frame":29.733333333333334,"value":[-6.49,-146.18]},{"frame":29.766666666666666,"value":[-4.5,-145.42]},{"frame":29.8,"value":[-5.92,-146.95]},{"frame":30,"value":[-2.95,-146.4]},{"frame":30.033333333333335,"value":[-3.5,-145.72]},{"frame":30.066666666666666,"value":[-6.49,-146.18]},{"frame":30.1,"value":[-5.89,-144.88]},{"frame":30.133333333333333,"value":[-7.03,-146.45]},{"frame":30.166666666666668,"value":[-4.84,-147.08]},{"frame":30.2,"value":[-4.04,-144.93]},{"frame":30.233333333333334,"value":[-3.83,-146.96]},{"frame":30.266666666666666,"value":[-6.49,-146.18]},{"frame":30.3,"value":[-4.5,-145.42]},{"frame":30.333333333333332,"value":[-5.92,-146.95]},{"frame":30.533333333333335,"value":[-2.95,-146.4]},{"frame":30.566666666666666,"value":[-3.5,-145.72]},{"frame":30.6,"value":[-6.49,-146.18]},{"frame":30.633333333333333,"value":[-5.89,-144.88]},{"frame":30.666666666666668,"value":[-7.03,-146.45]},{"frame":30.7,"value":[-4.84,-147.08]},{"frame":30.733333333333334,"value":[-4.04,-144.93]},{"frame":30.766666666666666,"value":[-3.83,-146.96]},{"frame":30.8,"value":[-6.49,-146.18]},{"frame":30.833333333333332,"value":[-4.5,-145.42]},{"frame":30.866666666666667,"value":[-5.92,-146.95]},{"frame":31,"value":[-2.95,-146.4]},{"frame":31.033333333333335,"value":[-3.5,-145.72]},{"frame":31.066666666666666,"value":[-6.49,-146.18]},{"frame":31.1,"value":[-5.89,-144.88]},{"frame":31.133333333333333,"value":[-7.03,-146.45]},{"frame":31.166666666666668,"value":[-4.84,-147.08]},{"frame":31.2,"value":[-4.04,-144.93]},{"frame":31.233333333333334,"value":[-3.83,-146.96]},{"frame":31.266666666666666,"value":[-6.49,-146.18]},{"frame":31.3,"value":[-4.5,-145.42]},{"frame":31.333333333333332,"value":[-5.92,-146.95]}]}},"end3Cbackground/boym5/boym5_eye":{"props":{"position":[{"frame":0,"value":[-0.324,19.02,0]},{"frame":0.03333333333333333,"value":[2.989,19.02,0]},{"frame":0.06666666666666667,"value":[-0.95,19.02,0]},{"frame":0.1,"value":[1.676,19.02,0]},{"frame":0.13333333333333333,"value":[-0.95,19.02,0]},{"frame":0.16666666666666666,"value":[2.989,19.02,0]},{"frame":0.2,"value":[-0.95,19.02,0]},{"frame":0.23333333333333334,"value":[1.676,19.02,0]},{"frame":0.26666666666666666,"value":[-0.95,19.02,0]},{"frame":0.3333333333333333,"value":[-0.324,19.02,0]},{"frame":0.36666666666666664,"value":[2.989,19.02,0]},{"frame":0.4,"value":[-0.95,19.02,0]},{"frame":0.43333333333333335,"value":[1.676,19.02,0]},{"frame":0.4666666666666667,"value":[-0.95,19.02,0]},{"frame":0.5,"value":[2.989,19.02,0]},{"frame":0.5333333333333333,"value":[-0.95,19.02,0]},{"frame":0.5666666666666667,"value":[1.676,19.02,0]},{"frame":0.6,"value":[-0.95,19.02,0]},{"frame":0.6666666666666666,"value":[-0.324,19.02,0]},{"frame":0.7,"value":[2.989,19.02,0]},{"frame":0.7333333333333333,"value":[-0.95,19.02,0]},{"frame":0.7666666666666667,"value":[1.676,19.02,0]},{"frame":0.8,"value":[-0.95,19.02,0]},{"frame":0.8333333333333334,"value":[2.989,19.02,0]},{"frame":0.8666666666666667,"value":[-0.95,19.02,0]},{"frame":0.9,"value":[1.676,19.02,0]},{"frame":0.9333333333333333,"value":[-0.95,19.02,0]},{"frame":1.0333333333333334,"value":[-0.324,19.02,0]},{"frame":1.0666666666666667,"value":[2.989,19.02,0]},{"frame":1.1,"value":[-0.95,19.02,0]},{"frame":1.1333333333333333,"value":[1.676,19.02,0]},{"frame":1.1666666666666667,"value":[-0.95,19.02,0]},{"frame":1.2,"value":[2.989,19.02,0]},{"frame":1.2333333333333334,"value":[-0.95,19.02,0]},{"frame":1.2666666666666666,"value":[1.676,19.02,0]},{"frame":1.3,"value":[-0.95,19.02,0]},{"frame":1.3666666666666667,"value":[-0.324,19.02,0]},{"frame":1.4,"value":[2.989,19.02,0]},{"frame":1.4333333333333333,"value":[-0.95,19.02,0]},{"frame":1.4666666666666666,"value":[1.676,19.02,0]},{"frame":1.5,"value":[-0.95,19.02,0]},{"frame":1.5333333333333334,"value":[2.989,19.02,0]},{"frame":1.5666666666666667,"value":[-0.95,19.02,0]},{"frame":1.6,"value":[1.676,19.02,0]},{"frame":1.6333333333333333,"value":[-0.95,19.02,0]},{"frame":1.7333333333333334,"value":[-0.324,19.02,0]},{"frame":1.7666666666666666,"value":[2.989,19.02,0]},{"frame":1.8,"value":[-0.95,19.02,0]},{"frame":1.8333333333333333,"value":[1.676,19.02,0]},{"frame":1.8666666666666667,"value":[-0.95,19.02,0]},{"frame":1.9,"value":[2.989,19.02,0]},{"frame":1.9333333333333333,"value":[-0.95,19.02,0]},{"frame":1.9666666666666666,"value":[1.676,19.02,0]},{"frame":2,"value":[-0.95,19.02,0]},{"frame":2.066666666666667,"value":[-0.324,19.02,0]},{"frame":2.1,"value":[2.989,19.02,0]},{"frame":2.1333333333333333,"value":[-0.95,19.02,0]},{"frame":2.1666666666666665,"value":[1.676,19.02,0]},{"frame":2.2,"value":[-0.95,19.02,0]},{"frame":2.2333333333333334,"value":[2.989,19.02,0]},{"frame":2.2666666666666666,"value":[-0.95,19.02,0]},{"frame":2.3,"value":[1.676,19.02,0]},{"frame":2.3333333333333335,"value":[-0.95,19.02,0]},{"frame":2.4,"value":[-0.324,19.02,0]},{"frame":2.433333333333333,"value":[2.989,19.02,0]},{"frame":2.466666666666667,"value":[-0.95,19.02,0]},{"frame":2.5,"value":[1.676,19.02,0]},{"frame":2.533333333333333,"value":[-0.95,19.02,0]},{"frame":2.566666666666667,"value":[2.989,19.02,0]},{"frame":2.6,"value":[-0.95,19.02,0]},{"frame":2.6333333333333333,"value":[1.676,19.02,0]},{"frame":2.6666666666666665,"value":[-0.95,19.02,0]},{"frame":2.7333333333333334,"value":[-0.324,19.02,0]},{"frame":2.7666666666666666,"value":[2.989,19.02,0]},{"frame":2.8,"value":[-0.95,19.02,0]},{"frame":2.8333333333333335,"value":[1.676,19.02,0]},{"frame":2.8666666666666667,"value":[-0.95,19.02,0]},{"frame":2.9,"value":[2.989,19.02,0]},{"frame":2.933333333333333,"value":[-0.95,19.02,0]},{"frame":2.966666666666667,"value":[1.676,19.02,0]},{"frame":3,"value":[-0.95,19.02,0]},{"frame":3.1,"value":[-0.324,19.02,0]},{"frame":3.1333333333333333,"value":[2.989,19.02,0]},{"frame":3.1666666666666665,"value":[-0.95,19.02,0]},{"frame":3.2,"value":[1.676,19.02,0]},{"frame":3.2333333333333334,"value":[-0.95,19.02,0]},{"frame":3.2666666666666666,"value":[2.989,19.02,0]},{"frame":3.3,"value":[-0.95,19.02,0]},{"frame":3.3333333333333335,"value":[1.676,19.02,0]},{"frame":3.3666666666666667,"value":[-0.95,19.02,0]},{"frame":3.433333333333333,"value":[-0.324,19.02,0]},{"frame":3.466666666666667,"value":[2.989,19.02,0]},{"frame":3.5,"value":[-0.95,19.02,0]},{"frame":3.533333333333333,"value":[1.676,19.02,0]},{"frame":3.566666666666667,"value":[-0.95,19.02,0]},{"frame":3.6,"value":[2.989,19.02,0]},{"frame":3.6333333333333333,"value":[-0.95,19.02,0]},{"frame":3.6666666666666665,"value":[1.676,19.02,0]},{"frame":3.7,"value":[-0.95,19.02,0]},{"frame":3.8,"value":[-0.324,19.02,0]},{"frame":3.8333333333333335,"value":[2.989,19.02,0]},{"frame":3.8666666666666667,"value":[-0.95,19.02,0]},{"frame":3.9,"value":[1.676,19.02,0]},{"frame":3.933333333333333,"value":[-0.95,19.02,0]},{"frame":3.966666666666667,"value":[2.989,19.02,0]},{"frame":4,"value":[-0.95,19.02,0]},{"frame":4.033333333333333,"value":[1.676,19.02,0]},{"frame":4.066666666666666,"value":[-0.95,19.02,0]},{"frame":4.133333333333334,"value":[-0.324,19.02,0]},{"frame":4.166666666666667,"value":[2.989,19.02,0]},{"frame":4.2,"value":[-0.95,19.02,0]},{"frame":4.233333333333333,"value":[1.676,19.02,0]},{"frame":4.266666666666667,"value":[-0.95,19.02,0]},{"frame":4.3,"value":[2.989,19.02,0]},{"frame":4.333333333333333,"value":[-0.95,19.02,0]},{"frame":4.366666666666666,"value":[1.676,19.02,0]},{"frame":4.4,"value":[-0.95,19.02,0]},{"frame":4.466666666666667,"value":[-0.324,19.02,0]},{"frame":4.5,"value":[2.989,19.02,0]},{"frame":4.533333333333333,"value":[-0.95,19.02,0]},{"frame":4.566666666666666,"value":[1.676,19.02,0]},{"frame":4.6,"value":[-0.95,19.02,0]},{"frame":4.633333333333334,"value":[2.989,19.02,0]},{"frame":4.666666666666667,"value":[-0.95,19.02,0]},{"frame":4.7,"value":[1.676,19.02,0]},{"frame":4.733333333333333,"value":[-0.95,19.02,0]},{"frame":4.8,"value":[-0.324,19.02,0]},{"frame":4.833333333333333,"value":[2.989,19.02,0]},{"frame":4.866666666666666,"value":[-0.95,19.02,0]},{"frame":4.9,"value":[1.676,19.02,0]},{"frame":4.933333333333334,"value":[-0.95,19.02,0]},{"frame":4.966666666666667,"value":[2.989,19.02,0]},{"frame":5,"value":[-0.95,19.02,0]},{"frame":5.033333333333333,"value":[1.676,19.02,0]},{"frame":5.066666666666666,"value":[-0.95,19.02,0]},{"frame":5.166666666666667,"value":[-0.324,19.02,0]},{"frame":5.2,"value":[2.989,19.02,0]},{"frame":5.233333333333333,"value":[-0.95,19.02,0]},{"frame":5.266666666666667,"value":[1.676,19.02,0]},{"frame":5.3,"value":[-0.95,19.02,0]},{"frame":5.333333333333333,"value":[2.989,19.02,0]},{"frame":5.366666666666666,"value":[-0.95,19.02,0]},{"frame":5.4,"value":[1.676,19.02,0]},{"frame":5.433333333333334,"value":[-0.95,19.02,0]},{"frame":5.5,"value":[-0.324,19.02,0]},{"frame":5.533333333333333,"value":[2.989,19.02,0]},{"frame":5.566666666666666,"value":[-0.95,19.02,0]},{"frame":5.6,"value":[1.676,19.02,0]},{"frame":5.633333333333334,"value":[-0.95,19.02,0]},{"frame":5.666666666666667,"value":[2.989,19.02,0]},{"frame":5.7,"value":[-0.95,19.02,0]},{"frame":5.733333333333333,"value":[1.676,19.02,0]},{"frame":5.766666666666667,"value":[-0.95,19.02,0]},{"frame":5.866666666666666,"value":[-0.324,19.02,0]},{"frame":5.9,"value":[2.989,19.02,0]},{"frame":5.933333333333334,"value":[-0.95,19.02,0]},{"frame":5.966666666666667,"value":[1.676,19.02,0]},{"frame":6,"value":[-0.95,19.02,0]},{"frame":6.033333333333333,"value":[2.989,19.02,0]},{"frame":6.066666666666666,"value":[-0.95,19.02,0]},{"frame":6.1,"value":[1.676,19.02,0]},{"frame":6.133333333333334,"value":[-0.95,19.02,0]},{"frame":6.2,"value":[-0.324,19.02,0]},{"frame":6.233333333333333,"value":[2.989,19.02,0]},{"frame":6.266666666666667,"value":[-0.95,19.02,0]},{"frame":6.3,"value":[1.676,19.02,0]},{"frame":6.333333333333333,"value":[-0.95,19.02,0]},{"frame":6.366666666666666,"value":[2.989,19.02,0]},{"frame":6.4,"value":[-0.95,19.02,0]},{"frame":6.433333333333334,"value":[1.676,19.02,0]},{"frame":6.466666666666667,"value":[-0.95,19.02,0]},{"frame":6.533333333333333,"value":[-0.324,19.02,0]},{"frame":6.566666666666666,"value":[2.989,19.02,0]},{"frame":6.6,"value":[-0.95,19.02,0]},{"frame":6.633333333333334,"value":[1.676,19.02,0]},{"frame":6.666666666666667,"value":[-0.95,19.02,0]},{"frame":6.7,"value":[2.989,19.02,0]},{"frame":6.733333333333333,"value":[-0.95,19.02,0]},{"frame":6.766666666666667,"value":[1.676,19.02,0]},{"frame":6.8,"value":[-0.95,19.02,0]},{"frame":6.866666666666666,"value":[-0.324,19.02,0]},{"frame":6.9,"value":[2.989,19.02,0]},{"frame":6.933333333333334,"value":[-0.95,19.02,0]},{"frame":6.966666666666667,"value":[1.676,19.02,0]},{"frame":7,"value":[-0.95,19.02,0]},{"frame":7.033333333333333,"value":[2.989,19.02,0]},{"frame":7.066666666666666,"value":[-0.95,19.02,0]},{"frame":7.1,"value":[1.676,19.02,0]},{"frame":7.133333333333334,"value":[-0.95,19.02,0]},{"frame":7.233333333333333,"value":[-0.324,19.02,0]},{"frame":7.266666666666667,"value":[2.989,19.02,0]},{"frame":7.3,"value":[-0.95,19.02,0]},{"frame":7.333333333333333,"value":[1.676,19.02,0]},{"frame":7.366666666666666,"value":[-0.95,19.02,0]},{"frame":7.4,"value":[2.989,19.02,0]},{"frame":7.433333333333334,"value":[-0.95,19.02,0]},{"frame":7.466666666666667,"value":[1.676,19.02,0]},{"frame":7.5,"value":[-0.95,19.02,0]},{"frame":7.566666666666666,"value":[-0.324,19.02,0]},{"frame":7.6,"value":[2.989,19.02,0]},{"frame":7.633333333333334,"value":[-0.95,19.02,0]},{"frame":7.666666666666667,"value":[1.676,19.02,0]},{"frame":7.7,"value":[-0.95,19.02,0]},{"frame":7.733333333333333,"value":[2.989,19.02,0]},{"frame":7.766666666666667,"value":[-0.95,19.02,0]},{"frame":7.8,"value":[1.676,19.02,0]},{"frame":7.833333333333333,"value":[-0.95,19.02,0]},{"frame":7.933333333333334,"value":[-0.324,19.02,0]},{"frame":7.966666666666667,"value":[2.989,19.02,0]},{"frame":8,"value":[-0.95,19.02,0]},{"frame":8.033333333333333,"value":[1.676,19.02,0]},{"frame":8.066666666666666,"value":[-0.95,19.02,0]},{"frame":8.1,"value":[2.989,19.02,0]},{"frame":8.133333333333333,"value":[-0.95,19.02,0]},{"frame":8.166666666666666,"value":[1.676,19.02,0]},{"frame":8.2,"value":[-0.95,19.02,0]},{"frame":8.333333333333334,"value":[-0.324,19.02,0]},{"frame":8.366666666666667,"value":[2.989,19.02,0]},{"frame":8.4,"value":[-0.95,19.02,0]},{"frame":8.433333333333334,"value":[1.676,19.02,0]},{"frame":8.466666666666667,"value":[-0.95,19.02,0]},{"frame":8.5,"value":[2.989,19.02,0]},{"frame":8.533333333333333,"value":[-0.95,19.02,0]},{"frame":8.566666666666666,"value":[1.676,19.02,0]},{"frame":8.6,"value":[-0.95,19.02,0]},{"frame":8.666666666666666,"value":[-0.324,19.02,0]},{"frame":8.7,"value":[2.989,19.02,0]},{"frame":8.733333333333333,"value":[-0.95,19.02,0]},{"frame":8.766666666666667,"value":[1.676,19.02,0]},{"frame":8.8,"value":[-0.95,19.02,0]},{"frame":8.833333333333334,"value":[2.989,19.02,0]},{"frame":8.866666666666667,"value":[-0.95,19.02,0]},{"frame":8.9,"value":[1.676,19.02,0]},{"frame":8.933333333333334,"value":[-0.95,19.02,0]},{"frame":9,"value":[-0.324,19.02,0]},{"frame":9.033333333333333,"value":[2.989,19.02,0]},{"frame":9.066666666666666,"value":[-0.95,19.02,0]},{"frame":9.1,"value":[1.676,19.02,0]},{"frame":9.133333333333333,"value":[-0.95,19.02,0]},{"frame":9.166666666666666,"value":[2.989,19.02,0]},{"frame":9.2,"value":[-0.95,19.02,0]},{"frame":9.233333333333333,"value":[1.676,19.02,0]},{"frame":9.266666666666667,"value":[-0.95,19.02,0]},{"frame":9.366666666666667,"value":[-0.324,19.02,0]},{"frame":9.4,"value":[2.989,19.02,0]},{"frame":9.433333333333334,"value":[-0.95,19.02,0]},{"frame":9.466666666666667,"value":[1.676,19.02,0]},{"frame":9.5,"value":[-0.95,19.02,0]},{"frame":9.533333333333333,"value":[2.989,19.02,0]},{"frame":9.566666666666666,"value":[-0.95,19.02,0]},{"frame":9.6,"value":[1.676,19.02,0]},{"frame":9.633333333333333,"value":[-0.95,19.02,0]},{"frame":9.7,"value":[-0.324,19.02,0]},{"frame":9.733333333333333,"value":[2.989,19.02,0]},{"frame":9.766666666666667,"value":[-0.95,19.02,0]},{"frame":9.8,"value":[1.676,19.02,0]},{"frame":9.833333333333334,"value":[-0.95,19.02,0]},{"frame":9.866666666666667,"value":[2.989,19.02,0]},{"frame":9.9,"value":[-0.95,19.02,0]},{"frame":9.933333333333334,"value":[1.676,19.02,0]},{"frame":9.966666666666667,"value":[-0.95,19.02,0]},{"frame":10.066666666666666,"value":[-0.324,19.02,0]},{"frame":10.1,"value":[2.989,19.02,0]},{"frame":10.133333333333333,"value":[-0.95,19.02,0]},{"frame":10.166666666666666,"value":[1.676,19.02,0]},{"frame":10.2,"value":[-0.95,19.02,0]},{"frame":10.233333333333333,"value":[2.989,19.02,0]},{"frame":10.266666666666667,"value":[-0.95,19.02,0]},{"frame":10.3,"value":[1.676,19.02,0]},{"frame":10.333333333333334,"value":[-0.95,19.02,0]},{"frame":10.4,"value":[-0.324,19.02,0]},{"frame":10.433333333333334,"value":[2.989,19.02,0]},{"frame":10.466666666666667,"value":[-0.95,19.02,0]},{"frame":10.5,"value":[1.676,19.02,0]},{"frame":10.533333333333333,"value":[-0.95,19.02,0]},{"frame":10.566666666666666,"value":[2.989,19.02,0]},{"frame":10.6,"value":[-0.95,19.02,0]},{"frame":10.633333333333333,"value":[1.676,19.02,0]},{"frame":10.666666666666666,"value":[-0.95,19.02,0]},{"frame":10.733333333333333,"value":[-0.324,19.02,0]},{"frame":10.766666666666667,"value":[2.989,19.02,0]},{"frame":10.8,"value":[-0.95,19.02,0]},{"frame":10.833333333333334,"value":[1.676,19.02,0]},{"frame":10.866666666666667,"value":[-0.95,19.02,0]},{"frame":10.9,"value":[2.989,19.02,0]},{"frame":10.933333333333334,"value":[-0.95,19.02,0]},{"frame":10.966666666666667,"value":[1.676,19.02,0]},{"frame":11,"value":[-0.95,19.02,0]},{"frame":11.066666666666666,"value":[-0.324,19.02,0]},{"frame":11.1,"value":[2.989,19.02,0]},{"frame":11.133333333333333,"value":[-0.95,19.02,0]},{"frame":11.166666666666666,"value":[1.676,19.02,0]},{"frame":11.2,"value":[-0.95,19.02,0]},{"frame":11.233333333333333,"value":[2.989,19.02,0]},{"frame":11.266666666666667,"value":[-0.95,19.02,0]},{"frame":11.3,"value":[1.676,19.02,0]},{"frame":11.333333333333334,"value":[-0.95,19.02,0]},{"frame":11.433333333333334,"value":[-0.324,19.02,0]},{"frame":11.466666666666667,"value":[2.989,19.02,0]},{"frame":11.5,"value":[-0.95,19.02,0]},{"frame":11.533333333333333,"value":[1.676,19.02,0]},{"frame":11.566666666666666,"value":[-0.95,19.02,0]},{"frame":11.6,"value":[2.989,19.02,0]},{"frame":11.633333333333333,"value":[-0.95,19.02,0]},{"frame":11.666666666666666,"value":[1.676,19.02,0]},{"frame":11.7,"value":[-0.95,19.02,0]},{"frame":11.766666666666667,"value":[-0.324,19.02,0]},{"frame":11.8,"value":[2.989,19.02,0]},{"frame":11.833333333333334,"value":[-0.95,19.02,0]},{"frame":11.866666666666667,"value":[1.676,19.02,0]},{"frame":11.9,"value":[-0.95,19.02,0]},{"frame":11.933333333333334,"value":[2.989,19.02,0]},{"frame":11.966666666666667,"value":[-0.95,19.02,0]},{"frame":12,"value":[1.676,19.02,0]},{"frame":12.033333333333333,"value":[-0.95,19.02,0]},{"frame":12.133333333333333,"value":[-0.324,19.02,0]},{"frame":12.166666666666666,"value":[2.989,19.02,0]},{"frame":12.2,"value":[-0.95,19.02,0]},{"frame":12.233333333333333,"value":[1.676,19.02,0]},{"frame":12.266666666666667,"value":[-0.95,19.02,0]},{"frame":12.3,"value":[2.989,19.02,0]},{"frame":12.333333333333334,"value":[-0.95,19.02,0]},{"frame":12.366666666666667,"value":[1.676,19.02,0]},{"frame":12.4,"value":[-0.95,19.02,0]},{"frame":12.5,"value":[-0.324,19.02,0]},{"frame":12.533333333333333,"value":[2.989,19.02,0]},{"frame":12.566666666666666,"value":[-0.95,19.02,0]},{"frame":12.6,"value":[1.676,19.02,0]},{"frame":12.633333333333333,"value":[-0.95,19.02,0]},{"frame":12.666666666666666,"value":[2.989,19.02,0]},{"frame":12.7,"value":[-0.95,19.02,0]},{"frame":12.733333333333333,"value":[1.676,19.02,0]},{"frame":12.766666666666667,"value":[-0.95,19.02,0]},{"frame":12.833333333333334,"value":[-0.324,19.02,0]},{"frame":12.866666666666667,"value":[2.989,19.02,0]},{"frame":12.9,"value":[-0.95,19.02,0]},{"frame":12.933333333333334,"value":[1.676,19.02,0]},{"frame":12.966666666666667,"value":[-0.95,19.02,0]},{"frame":13,"value":[2.989,19.02,0]},{"frame":13.033333333333333,"value":[-0.95,19.02,0]},{"frame":13.066666666666666,"value":[1.676,19.02,0]},{"frame":13.1,"value":[-0.95,19.02,0]},{"frame":13.166666666666666,"value":[-0.324,19.02,0]},{"frame":13.2,"value":[2.989,19.02,0]},{"frame":13.233333333333333,"value":[-0.95,19.02,0]},{"frame":13.266666666666667,"value":[1.676,19.02,0]},{"frame":13.3,"value":[-0.95,19.02,0]},{"frame":13.333333333333334,"value":[2.989,19.02,0]},{"frame":13.366666666666667,"value":[-0.95,19.02,0]},{"frame":13.4,"value":[1.676,19.02,0]},{"frame":13.433333333333334,"value":[-0.95,19.02,0]},{"frame":13.533333333333333,"value":[-0.324,19.02,0]},{"frame":13.566666666666666,"value":[2.989,19.02,0]},{"frame":13.6,"value":[-0.95,19.02,0]},{"frame":13.633333333333333,"value":[1.676,19.02,0]},{"frame":13.666666666666666,"value":[-0.95,19.02,0]},{"frame":13.7,"value":[2.989,19.02,0]},{"frame":13.733333333333333,"value":[-0.95,19.02,0]},{"frame":13.766666666666667,"value":[1.676,19.02,0]},{"frame":13.8,"value":[-0.95,19.02,0]},{"frame":13.866666666666667,"value":[-0.324,19.02,0]},{"frame":13.9,"value":[2.989,19.02,0]},{"frame":13.933333333333334,"value":[-0.95,19.02,0]},{"frame":13.966666666666667,"value":[1.676,19.02,0]},{"frame":14,"value":[-0.95,19.02,0]},{"frame":14.033333333333333,"value":[2.989,19.02,0]},{"frame":14.066666666666666,"value":[-0.95,19.02,0]},{"frame":14.1,"value":[1.676,19.02,0]},{"frame":14.133333333333333,"value":[-0.95,19.02,0]},{"frame":14.233333333333333,"value":[-0.324,19.02,0]},{"frame":14.266666666666667,"value":[2.989,19.02,0]},{"frame":14.3,"value":[-0.95,19.02,0]},{"frame":14.333333333333334,"value":[1.676,19.02,0]},{"frame":14.366666666666667,"value":[-0.95,19.02,0]},{"frame":14.4,"value":[2.989,19.02,0]},{"frame":14.433333333333334,"value":[-0.95,19.02,0]},{"frame":14.466666666666667,"value":[1.676,19.02,0]},{"frame":14.5,"value":[-0.95,19.02,0]},{"frame":14.566666666666666,"value":[-0.324,19.02,0]},{"frame":14.6,"value":[2.989,19.02,0]},{"frame":14.633333333333333,"value":[-0.95,19.02,0]},{"frame":14.666666666666666,"value":[1.676,19.02,0]},{"frame":14.7,"value":[-0.95,19.02,0]},{"frame":14.733333333333333,"value":[2.989,19.02,0]},{"frame":14.766666666666667,"value":[-0.95,19.02,0]},{"frame":14.8,"value":[1.676,19.02,0]},{"frame":14.833333333333334,"value":[-0.95,19.02,0]},{"frame":14.9,"value":[-0.324,19.02,0]},{"frame":14.933333333333334,"value":[2.989,19.02,0]},{"frame":14.966666666666667,"value":[-0.95,19.02,0]},{"frame":15,"value":[1.676,19.02,0]},{"frame":15.033333333333333,"value":[-0.95,19.02,0]},{"frame":15.066666666666666,"value":[2.989,19.02,0]},{"frame":15.1,"value":[-0.95,19.02,0]},{"frame":15.133333333333333,"value":[1.676,19.02,0]},{"frame":15.166666666666666,"value":[-0.95,19.02,0]},{"frame":15.233333333333333,"value":[-0.324,19.02,0]},{"frame":15.266666666666667,"value":[2.989,19.02,0]},{"frame":15.3,"value":[-0.95,19.02,0]},{"frame":15.333333333333334,"value":[1.676,19.02,0]},{"frame":15.366666666666667,"value":[-0.95,19.02,0]},{"frame":15.4,"value":[2.989,19.02,0]},{"frame":15.433333333333334,"value":[-0.95,19.02,0]},{"frame":15.466666666666667,"value":[1.676,19.02,0]},{"frame":15.5,"value":[-0.95,19.02,0]},{"frame":15.6,"value":[-0.324,19.02,0]},{"frame":15.633333333333333,"value":[2.989,19.02,0]},{"frame":15.666666666666666,"value":[-0.95,19.02,0]},{"frame":15.7,"value":[1.676,19.02,0]},{"frame":15.733333333333333,"value":[-0.95,19.02,0]},{"frame":15.766666666666667,"value":[2.989,19.02,0]},{"frame":15.8,"value":[-0.95,19.02,0]},{"frame":15.833333333333334,"value":[1.676,19.02,0]},{"frame":15.866666666666667,"value":[-0.95,19.02,0]},{"frame":15.933333333333334,"value":[-0.324,19.02,0]},{"frame":15.966666666666667,"value":[2.989,19.02,0]},{"frame":16,"value":[-0.95,19.02,0]},{"frame":16.033333333333335,"value":[1.676,19.02,0]},{"frame":16.066666666666666,"value":[-0.95,19.02,0]},{"frame":16.1,"value":[2.989,19.02,0]},{"frame":16.133333333333333,"value":[-0.95,19.02,0]},{"frame":16.166666666666668,"value":[1.676,19.02,0]},{"frame":16.2,"value":[-0.95,19.02,0]},{"frame":16.3,"value":[-0.324,19.02,0]},{"frame":16.333333333333332,"value":[2.989,19.02,0]},{"frame":16.366666666666667,"value":[-0.95,19.02,0]},{"frame":16.4,"value":[1.676,19.02,0]},{"frame":16.433333333333334,"value":[-0.95,19.02,0]},{"frame":16.466666666666665,"value":[2.989,19.02,0]},{"frame":16.5,"value":[-0.95,19.02,0]},{"frame":16.533333333333335,"value":[1.676,19.02,0]},{"frame":16.566666666666666,"value":[-0.95,19.02,0]},{"frame":16.7,"value":[-0.324,19.02,0]},{"frame":16.733333333333334,"value":[2.989,19.02,0]},{"frame":16.766666666666666,"value":[-0.95,19.02,0]},{"frame":16.8,"value":[1.676,19.02,0]},{"frame":16.833333333333332,"value":[-0.95,19.02,0]},{"frame":16.866666666666667,"value":[2.989,19.02,0]},{"frame":16.9,"value":[-0.95,19.02,0]},{"frame":16.933333333333334,"value":[1.676,19.02,0]},{"frame":16.966666666666665,"value":[-0.95,19.02,0]},{"frame":17.033333333333335,"value":[-0.324,19.02,0]},{"frame":17.066666666666666,"value":[2.989,19.02,0]},{"frame":17.1,"value":[-0.95,19.02,0]},{"frame":17.133333333333333,"value":[1.676,19.02,0]},{"frame":17.166666666666668,"value":[-0.95,19.02,0]},{"frame":17.2,"value":[2.989,19.02,0]},{"frame":17.233333333333334,"value":[-0.95,19.02,0]},{"frame":17.266666666666666,"value":[1.676,19.02,0]},{"frame":17.3,"value":[-0.95,19.02,0]},{"frame":17.366666666666667,"value":[-0.324,19.02,0]},{"frame":17.4,"value":[2.989,19.02,0]},{"frame":17.433333333333334,"value":[-0.95,19.02,0]},{"frame":17.466666666666665,"value":[1.676,19.02,0]},{"frame":17.5,"value":[-0.95,19.02,0]},{"frame":17.533333333333335,"value":[2.989,19.02,0]},{"frame":17.566666666666666,"value":[-0.95,19.02,0]},{"frame":17.6,"value":[1.676,19.02,0]},{"frame":17.633333333333333,"value":[-0.95,19.02,0]},{"frame":17.733333333333334,"value":[-0.324,19.02,0]},{"frame":17.766666666666666,"value":[2.989,19.02,0]},{"frame":17.8,"value":[-0.95,19.02,0]},{"frame":17.833333333333332,"value":[1.676,19.02,0]},{"frame":17.866666666666667,"value":[-0.95,19.02,0]},{"frame":17.9,"value":[2.989,19.02,0]},{"frame":17.933333333333334,"value":[-0.95,19.02,0]},{"frame":17.966666666666665,"value":[1.676,19.02,0]},{"frame":18,"value":[-0.95,19.02,0]},{"frame":18.066666666666666,"value":[-0.324,19.02,0]},{"frame":18.1,"value":[2.989,19.02,0]},{"frame":18.133333333333333,"value":[-0.95,19.02,0]},{"frame":18.166666666666668,"value":[1.676,19.02,0]},{"frame":18.2,"value":[-0.95,19.02,0]},{"frame":18.233333333333334,"value":[2.989,19.02,0]},{"frame":18.266666666666666,"value":[-0.95,19.02,0]},{"frame":18.3,"value":[1.676,19.02,0]},{"frame":18.333333333333332,"value":[-0.95,19.02,0]},{"frame":18.433333333333334,"value":[-0.324,19.02,0]},{"frame":18.466666666666665,"value":[2.989,19.02,0]},{"frame":18.5,"value":[-0.95,19.02,0]},{"frame":18.533333333333335,"value":[1.676,19.02,0]},{"frame":18.566666666666666,"value":[-0.95,19.02,0]},{"frame":18.6,"value":[2.989,19.02,0]},{"frame":18.633333333333333,"value":[-0.95,19.02,0]},{"frame":18.666666666666668,"value":[1.676,19.02,0]},{"frame":18.7,"value":[-0.95,19.02,0]},{"frame":18.766666666666666,"value":[-0.324,19.02,0]},{"frame":18.8,"value":[2.989,19.02,0]},{"frame":18.833333333333332,"value":[-0.95,19.02,0]},{"frame":18.866666666666667,"value":[1.676,19.02,0]},{"frame":18.9,"value":[-0.95,19.02,0]},{"frame":18.933333333333334,"value":[2.989,19.02,0]},{"frame":18.966666666666665,"value":[-0.95,19.02,0]},{"frame":19,"value":[1.676,19.02,0]},{"frame":19.033333333333335,"value":[-0.95,19.02,0]},{"frame":19.1,"value":[-0.324,19.02,0]},{"frame":19.133333333333333,"value":[2.989,19.02,0]},{"frame":19.166666666666668,"value":[-0.95,19.02,0]},{"frame":19.2,"value":[1.676,19.02,0]},{"frame":19.233333333333334,"value":[-0.95,19.02,0]},{"frame":19.266666666666666,"value":[2.989,19.02,0]},{"frame":19.3,"value":[-0.95,19.02,0]},{"frame":19.333333333333332,"value":[1.676,19.02,0]},{"frame":19.366666666666667,"value":[-0.95,19.02,0]},{"frame":19.433333333333334,"value":[-0.324,19.02,0]},{"frame":19.466666666666665,"value":[2.989,19.02,0]},{"frame":19.5,"value":[-0.95,19.02,0]},{"frame":19.533333333333335,"value":[1.676,19.02,0]},{"frame":19.566666666666666,"value":[-0.95,19.02,0]},{"frame":19.6,"value":[2.989,19.02,0]},{"frame":19.633333333333333,"value":[-0.95,19.02,0]},{"frame":19.666666666666668,"value":[1.676,19.02,0]},{"frame":19.7,"value":[-0.95,19.02,0]},{"frame":19.8,"value":[-0.324,19.02,0]},{"frame":19.833333333333332,"value":[2.989,19.02,0]},{"frame":19.866666666666667,"value":[-0.95,19.02,0]},{"frame":19.9,"value":[1.676,19.02,0]},{"frame":19.933333333333334,"value":[-0.95,19.02,0]},{"frame":19.966666666666665,"value":[2.989,19.02,0]},{"frame":20,"value":[-0.95,19.02,0]},{"frame":20.033333333333335,"value":[1.676,19.02,0]},{"frame":20.066666666666666,"value":[-0.95,19.02,0]},{"frame":20.133333333333333,"value":[-0.324,19.02,0]},{"frame":20.166666666666668,"value":[2.989,19.02,0]},{"frame":20.2,"value":[-0.95,19.02,0]},{"frame":20.233333333333334,"value":[1.676,19.02,0]},{"frame":20.266666666666666,"value":[-0.95,19.02,0]},{"frame":20.3,"value":[2.989,19.02,0]},{"frame":20.333333333333332,"value":[-0.95,19.02,0]},{"frame":20.366666666666667,"value":[1.676,19.02,0]},{"frame":20.4,"value":[-0.95,19.02,0]},{"frame":20.5,"value":[-0.324,19.02,0]},{"frame":20.533333333333335,"value":[2.989,19.02,0]},{"frame":20.566666666666666,"value":[-0.95,19.02,0]},{"frame":20.6,"value":[1.676,19.02,0]},{"frame":20.633333333333333,"value":[-0.95,19.02,0]},{"frame":20.666666666666668,"value":[2.989,19.02,0]},{"frame":20.7,"value":[-0.95,19.02,0]},{"frame":20.733333333333334,"value":[1.676,19.02,0]},{"frame":20.766666666666666,"value":[-0.95,19.02,0]},{"frame":20.866666666666667,"value":[-0.324,19.02,0]},{"frame":20.9,"value":[2.989,19.02,0]},{"frame":20.933333333333334,"value":[-0.95,19.02,0]},{"frame":20.966666666666665,"value":[1.676,19.02,0]},{"frame":21,"value":[-0.95,19.02,0]},{"frame":21.033333333333335,"value":[2.989,19.02,0]},{"frame":21.066666666666666,"value":[-0.95,19.02,0]},{"frame":21.1,"value":[1.676,19.02,0]},{"frame":21.133333333333333,"value":[-0.95,19.02,0]},{"frame":21.2,"value":[-0.324,19.02,0]},{"frame":21.233333333333334,"value":[2.989,19.02,0]},{"frame":21.266666666666666,"value":[-0.95,19.02,0]},{"frame":21.3,"value":[1.676,19.02,0]},{"frame":21.333333333333332,"value":[-0.95,19.02,0]},{"frame":21.366666666666667,"value":[2.989,19.02,0]},{"frame":21.4,"value":[-0.95,19.02,0]},{"frame":21.433333333333334,"value":[1.676,19.02,0]},{"frame":21.466666666666665,"value":[-0.95,19.02,0]},{"frame":21.533333333333335,"value":[-0.324,19.02,0]},{"frame":21.566666666666666,"value":[2.989,19.02,0]},{"frame":21.6,"value":[-0.95,19.02,0]},{"frame":21.633333333333333,"value":[1.676,19.02,0]},{"frame":21.666666666666668,"value":[-0.95,19.02,0]},{"frame":21.7,"value":[2.989,19.02,0]},{"frame":21.733333333333334,"value":[-0.95,19.02,0]},{"frame":21.766666666666666,"value":[1.676,19.02,0]},{"frame":21.8,"value":[-0.95,19.02,0]},{"frame":21.9,"value":[-0.324,19.02,0]},{"frame":21.933333333333334,"value":[2.989,19.02,0]},{"frame":21.966666666666665,"value":[-0.95,19.02,0]},{"frame":22,"value":[1.676,19.02,0]},{"frame":22.033333333333335,"value":[-0.95,19.02,0]},{"frame":22.066666666666666,"value":[2.989,19.02,0]},{"frame":22.1,"value":[-0.95,19.02,0]},{"frame":22.133333333333333,"value":[1.676,19.02,0]},{"frame":22.166666666666668,"value":[-0.95,19.02,0]},{"frame":22.233333333333334,"value":[-0.324,19.02,0]},{"frame":22.266666666666666,"value":[2.989,19.02,0]},{"frame":22.3,"value":[-0.95,19.02,0]},{"frame":22.333333333333332,"value":[1.676,19.02,0]},{"frame":22.366666666666667,"value":[-0.95,19.02,0]},{"frame":22.4,"value":[2.989,19.02,0]},{"frame":22.433333333333334,"value":[-0.95,19.02,0]},{"frame":22.466666666666665,"value":[1.676,19.02,0]},{"frame":22.5,"value":[-0.95,19.02,0]},{"frame":22.6,"value":[-0.324,19.02,0]},{"frame":22.633333333333333,"value":[2.989,19.02,0]},{"frame":22.666666666666668,"value":[-0.95,19.02,0]},{"frame":22.7,"value":[1.676,19.02,0]},{"frame":22.733333333333334,"value":[-0.95,19.02,0]},{"frame":22.766666666666666,"value":[2.989,19.02,0]},{"frame":22.8,"value":[-0.95,19.02,0]},{"frame":22.833333333333332,"value":[1.676,19.02,0]},{"frame":22.866666666666667,"value":[-0.95,19.02,0]},{"frame":22.933333333333334,"value":[-0.324,19.02,0]},{"frame":22.966666666666665,"value":[2.989,19.02,0]},{"frame":23,"value":[-0.95,19.02,0]},{"frame":23.033333333333335,"value":[1.676,19.02,0]},{"frame":23.066666666666666,"value":[-0.95,19.02,0]},{"frame":23.1,"value":[2.989,19.02,0]},{"frame":23.133333333333333,"value":[-0.95,19.02,0]},{"frame":23.166666666666668,"value":[1.676,19.02,0]},{"frame":23.2,"value":[-0.95,19.02,0]},{"frame":23.266666666666666,"value":[-0.324,19.02,0]},{"frame":23.3,"value":[2.989,19.02,0]},{"frame":23.333333333333332,"value":[-0.95,19.02,0]},{"frame":23.366666666666667,"value":[1.676,19.02,0]},{"frame":23.4,"value":[-0.95,19.02,0]},{"frame":23.433333333333334,"value":[2.989,19.02,0]},{"frame":23.466666666666665,"value":[-0.95,19.02,0]},{"frame":23.5,"value":[1.676,19.02,0]},{"frame":23.533333333333335,"value":[-0.95,19.02,0]},{"frame":23.6,"value":[-0.324,19.02,0]},{"frame":23.633333333333333,"value":[2.989,19.02,0]},{"frame":23.666666666666668,"value":[-0.95,19.02,0]},{"frame":23.7,"value":[1.676,19.02,0]},{"frame":23.733333333333334,"value":[-0.95,19.02,0]},{"frame":23.766666666666666,"value":[2.989,19.02,0]},{"frame":23.8,"value":[-0.95,19.02,0]},{"frame":23.833333333333332,"value":[1.676,19.02,0]},{"frame":23.866666666666667,"value":[-0.95,19.02,0]},{"frame":23.966666666666665,"value":[-0.324,19.02,0]},{"frame":24,"value":[2.989,19.02,0]},{"frame":24.033333333333335,"value":[-0.95,19.02,0]},{"frame":24.066666666666666,"value":[1.676,19.02,0]},{"frame":24.1,"value":[-0.95,19.02,0]},{"frame":24.133333333333333,"value":[2.989,19.02,0]},{"frame":24.166666666666668,"value":[-0.95,19.02,0]},{"frame":24.2,"value":[1.676,19.02,0]},{"frame":24.233333333333334,"value":[-0.95,19.02,0]},{"frame":24.3,"value":[-0.324,19.02,0]},{"frame":24.333333333333332,"value":[2.989,19.02,0]},{"frame":24.366666666666667,"value":[-0.95,19.02,0]},{"frame":24.4,"value":[1.676,19.02,0]},{"frame":24.433333333333334,"value":[-0.95,19.02,0]},{"frame":24.466666666666665,"value":[2.989,19.02,0]},{"frame":24.5,"value":[-0.95,19.02,0]},{"frame":24.533333333333335,"value":[1.676,19.02,0]},{"frame":24.566666666666666,"value":[-0.95,19.02,0]},{"frame":24.666666666666668,"value":[-0.324,19.02,0]},{"frame":24.7,"value":[2.989,19.02,0]},{"frame":24.733333333333334,"value":[-0.95,19.02,0]},{"frame":24.766666666666666,"value":[1.676,19.02,0]},{"frame":24.8,"value":[-0.95,19.02,0]},{"frame":24.833333333333332,"value":[2.989,19.02,0]},{"frame":24.866666666666667,"value":[-0.95,19.02,0]},{"frame":24.9,"value":[1.676,19.02,0]},{"frame":24.933333333333334,"value":[-0.95,19.02,0]},{"frame":25.133333333333333,"value":[-0.324,19.02,0]},{"frame":25.166666666666668,"value":[2.989,19.02,0]},{"frame":25.2,"value":[-0.95,19.02,0]},{"frame":25.233333333333334,"value":[1.676,19.02,0]},{"frame":25.266666666666666,"value":[-0.95,19.02,0]},{"frame":25.3,"value":[2.989,19.02,0]},{"frame":25.333333333333332,"value":[-0.95,19.02,0]},{"frame":25.366666666666667,"value":[1.676,19.02,0]},{"frame":25.4,"value":[-0.95,19.02,0]},{"frame":25.466666666666665,"value":[-0.324,19.02,0]},{"frame":25.5,"value":[2.989,19.02,0]},{"frame":25.533333333333335,"value":[-0.95,19.02,0]},{"frame":25.566666666666666,"value":[1.676,19.02,0]},{"frame":25.6,"value":[-0.95,19.02,0]},{"frame":25.633333333333333,"value":[2.989,19.02,0]},{"frame":25.666666666666668,"value":[-0.95,19.02,0]},{"frame":25.7,"value":[1.676,19.02,0]},{"frame":25.733333333333334,"value":[-0.95,19.02,0]},{"frame":25.8,"value":[-0.324,19.02,0]},{"frame":25.833333333333332,"value":[2.989,19.02,0]},{"frame":25.866666666666667,"value":[-0.95,19.02,0]},{"frame":25.9,"value":[1.676,19.02,0]},{"frame":25.933333333333334,"value":[-0.95,19.02,0]},{"frame":25.966666666666665,"value":[2.989,19.02,0]},{"frame":26,"value":[-0.95,19.02,0]},{"frame":26.033333333333335,"value":[1.676,19.02,0]},{"frame":26.066666666666666,"value":[-0.95,19.02,0]},{"frame":26.166666666666668,"value":[-0.324,19.02,0]},{"frame":26.2,"value":[2.989,19.02,0]},{"frame":26.233333333333334,"value":[-0.95,19.02,0]},{"frame":26.266666666666666,"value":[1.676,19.02,0]},{"frame":26.3,"value":[-0.95,19.02,0]},{"frame":26.333333333333332,"value":[2.989,19.02,0]},{"frame":26.366666666666667,"value":[-0.95,19.02,0]},{"frame":26.4,"value":[1.676,19.02,0]},{"frame":26.433333333333334,"value":[-0.95,19.02,0]},{"frame":26.5,"value":[-0.324,19.02,0]},{"frame":26.533333333333335,"value":[2.989,19.02,0]},{"frame":26.566666666666666,"value":[-0.95,19.02,0]},{"frame":26.6,"value":[1.676,19.02,0]},{"frame":26.633333333333333,"value":[-0.95,19.02,0]},{"frame":26.666666666666668,"value":[2.989,19.02,0]},{"frame":26.7,"value":[-0.95,19.02,0]},{"frame":26.733333333333334,"value":[1.676,19.02,0]},{"frame":26.766666666666666,"value":[-0.95,19.02,0]},{"frame":26.866666666666667,"value":[-0.324,19.02,0]},{"frame":26.9,"value":[2.989,19.02,0]},{"frame":26.933333333333334,"value":[-0.95,19.02,0]},{"frame":26.966666666666665,"value":[1.676,19.02,0]},{"frame":27,"value":[-0.95,19.02,0]},{"frame":27.033333333333335,"value":[2.989,19.02,0]},{"frame":27.066666666666666,"value":[-0.95,19.02,0]},{"frame":27.1,"value":[1.676,19.02,0]},{"frame":27.133333333333333,"value":[-0.95,19.02,0]},{"frame":27.2,"value":[-0.324,19.02,0]},{"frame":27.233333333333334,"value":[2.989,19.02,0]},{"frame":27.266666666666666,"value":[-0.95,19.02,0]},{"frame":27.3,"value":[1.676,19.02,0]},{"frame":27.333333333333332,"value":[-0.95,19.02,0]},{"frame":27.366666666666667,"value":[2.989,19.02,0]},{"frame":27.4,"value":[-0.95,19.02,0]},{"frame":27.433333333333334,"value":[1.676,19.02,0]},{"frame":27.466666666666665,"value":[-0.95,19.02,0]},{"frame":27.533333333333335,"value":[-0.324,19.02,0]},{"frame":27.566666666666666,"value":[2.989,19.02,0]},{"frame":27.6,"value":[-0.95,19.02,0]},{"frame":27.633333333333333,"value":[1.676,19.02,0]},{"frame":27.666666666666668,"value":[-0.95,19.02,0]},{"frame":27.7,"value":[2.989,19.02,0]},{"frame":27.733333333333334,"value":[-0.95,19.02,0]},{"frame":27.766666666666666,"value":[1.676,19.02,0]},{"frame":27.8,"value":[-0.95,19.02,0]},{"frame":27.866666666666667,"value":[-0.324,19.02,0]},{"frame":27.9,"value":[2.989,19.02,0]},{"frame":27.933333333333334,"value":[-0.95,19.02,0]},{"frame":27.966666666666665,"value":[1.676,19.02,0]},{"frame":28,"value":[-0.95,19.02,0]},{"frame":28.033333333333335,"value":[2.989,19.02,0]},{"frame":28.066666666666666,"value":[-0.95,19.02,0]},{"frame":28.1,"value":[1.676,19.02,0]},{"frame":28.133333333333333,"value":[-0.95,19.02,0]},{"frame":28.233333333333334,"value":[-0.324,19.02,0]},{"frame":28.266666666666666,"value":[2.989,19.02,0]},{"frame":28.3,"value":[-0.95,19.02,0]},{"frame":28.333333333333332,"value":[1.676,19.02,0]},{"frame":28.366666666666667,"value":[-0.95,19.02,0]},{"frame":28.4,"value":[2.989,19.02,0]},{"frame":28.433333333333334,"value":[-0.95,19.02,0]},{"frame":28.466666666666665,"value":[1.676,19.02,0]},{"frame":28.5,"value":[-0.95,19.02,0]},{"frame":28.566666666666666,"value":[-0.324,19.02,0]},{"frame":28.6,"value":[2.989,19.02,0]},{"frame":28.633333333333333,"value":[-0.95,19.02,0]},{"frame":28.666666666666668,"value":[1.676,19.02,0]},{"frame":28.7,"value":[-0.95,19.02,0]},{"frame":28.733333333333334,"value":[2.989,19.02,0]},{"frame":28.766666666666666,"value":[-0.95,19.02,0]},{"frame":28.8,"value":[1.676,19.02,0]},{"frame":28.833333333333332,"value":[-0.95,19.02,0]},{"frame":28.933333333333334,"value":[-0.324,19.02,0]},{"frame":28.966666666666665,"value":[2.989,19.02,0]},{"frame":29,"value":[-0.95,19.02,0]},{"frame":29.033333333333335,"value":[1.676,19.02,0]},{"frame":29.066666666666666,"value":[-0.95,19.02,0]},{"frame":29.1,"value":[2.989,19.02,0]},{"frame":29.133333333333333,"value":[-0.95,19.02,0]},{"frame":29.166666666666668,"value":[1.676,19.02,0]},{"frame":29.2,"value":[-0.95,19.02,0]}]}},"////":{"props":{"position":[{"frame":4.133333333333334,"value":[-0.324,19.02,0]},{"frame":4.166666666666667,"value":[2.989,19.02,0]},{"frame":4.2,"value":[-0.95,19.02,0]},{"frame":4.233333333333333,"value":[1.676,19.02,0]},{"frame":4.266666666666667,"value":[-0.95,19.02,0]},{"frame":4.3,"value":[2.989,19.02,0]},{"frame":4.333333333333333,"value":[-0.95,19.02,0]},{"frame":4.366666666666666,"value":[1.676,19.02,0]},{"frame":4.4,"value":[-0.95,19.02,0]},{"frame":4.466666666666667,"value":[-0.324,19.02,0]},{"frame":4.5,"value":[2.989,19.02,0]},{"frame":4.533333333333333,"value":[-0.95,19.02,0]},{"frame":4.566666666666666,"value":[1.676,19.02,0]},{"frame":4.6,"value":[-0.95,19.02,0]},{"frame":4.633333333333334,"value":[2.989,19.02,0]},{"frame":4.666666666666667,"value":[-0.95,19.02,0]},{"frame":4.7,"value":[1.676,19.02,0]},{"frame":4.733333333333333,"value":[-0.95,19.02,0]},{"frame":4.8,"value":[-0.324,19.02,0]},{"frame":4.833333333333333,"value":[2.989,19.02,0]},{"frame":4.866666666666666,"value":[-0.95,19.02,0]},{"frame":4.9,"value":[1.676,19.02,0]},{"frame":4.933333333333334,"value":[-0.95,19.02,0]},{"frame":4.966666666666667,"value":[2.989,19.02,0]},{"frame":5,"value":[-0.95,19.02,0]},{"frame":5.033333333333333,"value":[1.676,19.02,0]},{"frame":5.066666666666666,"value":[-0.95,19.02,0]},{"frame":5.166666666666667,"value":[-0.324,19.02,0]},{"frame":5.2,"value":[2.989,19.02,0]},{"frame":5.233333333333333,"value":[-0.95,19.02,0]},{"frame":5.266666666666667,"value":[1.676,19.02,0]},{"frame":5.3,"value":[-0.95,19.02,0]},{"frame":5.333333333333333,"value":[2.989,19.02,0]},{"frame":5.366666666666666,"value":[-0.95,19.02,0]},{"frame":5.4,"value":[1.676,19.02,0]},{"frame":5.433333333333334,"value":[-0.95,19.02,0]},{"frame":5.5,"value":[-0.324,19.02,0]},{"frame":5.533333333333333,"value":[2.989,19.02,0]},{"frame":5.566666666666666,"value":[-0.95,19.02,0]},{"frame":5.6,"value":[1.676,19.02,0]},{"frame":5.633333333333334,"value":[-0.95,19.02,0]},{"frame":5.666666666666667,"value":[2.989,19.02,0]},{"frame":5.7,"value":[-0.95,19.02,0]},{"frame":5.733333333333333,"value":[1.676,19.02,0]},{"frame":5.766666666666667,"value":[-0.95,19.02,0]},{"frame":5.866666666666666,"value":[-0.324,19.02,0]},{"frame":5.9,"value":[2.989,19.02,0]},{"frame":5.933333333333334,"value":[-0.95,19.02,0]},{"frame":5.966666666666667,"value":[1.676,19.02,0]},{"frame":6,"value":[-0.95,19.02,0]},{"frame":6.033333333333333,"value":[2.989,19.02,0]},{"frame":6.066666666666666,"value":[-0.95,19.02,0]},{"frame":6.1,"value":[1.676,19.02,0]},{"frame":6.133333333333334,"value":[-0.95,19.02,0]},{"frame":6.2,"value":[-0.324,19.02,0]},{"frame":6.233333333333333,"value":[2.989,19.02,0]},{"frame":6.266666666666667,"value":[-0.95,19.02,0]},{"frame":6.3,"value":[1.676,19.02,0]},{"frame":6.333333333333333,"value":[-0.95,19.02,0]},{"frame":6.366666666666666,"value":[2.989,19.02,0]},{"frame":6.4,"value":[-0.95,19.02,0]},{"frame":6.433333333333334,"value":[1.676,19.02,0]},{"frame":6.466666666666667,"value":[-0.95,19.02,0]},{"frame":6.533333333333333,"value":[-0.324,19.02,0]},{"frame":6.566666666666666,"value":[2.989,19.02,0]},{"frame":6.6,"value":[-0.95,19.02,0]},{"frame":6.633333333333334,"value":[1.676,19.02,0]},{"frame":6.666666666666667,"value":[-0.95,19.02,0]},{"frame":6.7,"value":[2.989,19.02,0]},{"frame":6.733333333333333,"value":[-0.95,19.02,0]},{"frame":6.766666666666667,"value":[1.676,19.02,0]},{"frame":6.8,"value":[-0.95,19.02,0]},{"frame":6.866666666666666,"value":[-0.324,19.02,0]},{"frame":6.9,"value":[2.989,19.02,0]},{"frame":6.933333333333334,"value":[-0.95,19.02,0]},{"frame":6.966666666666667,"value":[1.676,19.02,0]},{"frame":7,"value":[-0.95,19.02,0]},{"frame":7.033333333333333,"value":[2.989,19.02,0]},{"frame":7.066666666666666,"value":[-0.95,19.02,0]},{"frame":7.1,"value":[1.676,19.02,0]},{"frame":7.133333333333334,"value":[-0.95,19.02,0]},{"frame":7.233333333333333,"value":[-0.324,19.02,0]},{"frame":7.266666666666667,"value":[2.989,19.02,0]},{"frame":7.3,"value":[-0.95,19.02,0]},{"frame":7.333333333333333,"value":[1.676,19.02,0]},{"frame":7.366666666666666,"value":[-0.95,19.02,0]},{"frame":7.4,"value":[2.989,19.02,0]},{"frame":7.433333333333334,"value":[-0.95,19.02,0]},{"frame":7.466666666666667,"value":[1.676,19.02,0]},{"frame":7.5,"value":[-0.95,19.02,0]},{"frame":7.566666666666666,"value":[-0.324,19.02,0]},{"frame":7.6,"value":[2.989,19.02,0]},{"frame":7.633333333333334,"value":[-0.95,19.02,0]},{"frame":7.666666666666667,"value":[1.676,19.02,0]},{"frame":7.7,"value":[-0.95,19.02,0]},{"frame":7.733333333333333,"value":[2.989,19.02,0]},{"frame":7.766666666666667,"value":[-0.95,19.02,0]},{"frame":7.8,"value":[1.676,19.02,0]},{"frame":7.833333333333333,"value":[-0.95,19.02,0]},{"frame":7.933333333333334,"value":[-0.324,19.02,0]},{"frame":7.966666666666667,"value":[2.989,19.02,0]},{"frame":8,"value":[-0.95,19.02,0]},{"frame":8.033333333333333,"value":[1.676,19.02,0]},{"frame":8.066666666666666,"value":[-0.95,19.02,0]},{"frame":8.1,"value":[2.989,19.02,0]},{"frame":8.133333333333333,"value":[-0.95,19.02,0]},{"frame":8.166666666666666,"value":[1.676,19.02,0]},{"frame":8.2,"value":[-0.95,19.02,0]}]}}}}]],0,0,[],[],[]],[[[11,"end",null],[12,"End1Cbackground",false,[-2,-3,-4,-5,-6,-7,-8,-9,-10,-11,-12,-13,-14],[[7,-1,[52]]],[5,716,600]],[13,"bg",[-22,-23,-24,-25,-26,1,-27,-28],[[25,-19,-18,-17,-16,-15,62],[26,-20,[64,65,66,67,68,69],63],[27,0.6,true,true,true,-21,70]],[4,4280228890]],[4,"End2Cbackground",false,1,[-30,-31,-32,-33,-34,-35,-36,-37,-38,-39],[[0,-29,[42],43]],[5,716,600]],[4,"end3Cbackground",false,2,[-41,-42,-43],[[7,-40,[61]]],[5,716,285]],[14,"Canvas","a5esZu+45LA5mBpvttspPD",[-46],[[28,true,false,-44,[5,768,1040]],[29,45,-45]],[5,768,1040],[384,520,0,0,0,0,1,1,1,1]],[15,"Main Camera",512,5,[2],[[30,7,-1,-47,[4,4280228890]]],[4,4280228890],[5,960,640]],[23,"hero",2,[[-48,[31,-49]],1,4],[5,32,32],[0,-32.821,0,0,0,0,1,1.5,1.5,1]],[16,"boym5",4,[-51],[[0,-50,[57],58]],[5,615,381],[0,10.715,0,0,0,0,1,1,1,1]],[32,"New Node",[5],[0,0,0],[0,0,0,0,0,0,1,1,1,1]],[1,"lightEnd",false,2,[[0,-52,[0],1]],[5,70,99],[0,63.523,0,0,0,0,1,3,3,1]],[24,"richCopy",false,2,[-53],[5,31,32],[0,-32.821,0,0,0,0,1,1.5,1.5,1]],[8,11,[2]],[8,7,[3]],[17,"controlbalck",false,2],[18,"blackscreen",false,2,[[0,-54,[4],5]],[4,4280228890],[5,2,2],[0,0,0,0,0,0,1,411.598,528.128,411.598]],[5,"End1Cbackground",1,[[0,-55,[6],7]],[5,716,600]],[1,"boym1glow",false,1,[[0,-56,[8],9]],[5,405,457],[-147.395,-138.462,0,0,0,0,1,1,1,1]],[2,"nvshen",1,[[0,-57,[10],11]],[5,373,286],[184.933,153.112,0,0,0,0,1,1,1,1]],[1,"boym1",false,1,[[0,-58,[12],13]],[5,351,395],[-154.35,-138.532,0,0,0,0,1,1,1,1]],[1,"mofa1",false,1,[[0,-59,[14],15]],[5,733,694],[-32.799,-67.011,0,0,0,0,1,1,1,1]],[1,"boym2",false,1,[[0,-60,[16],17]],[5,423,440],[-186.35,-141.531,0,0,0,0,1,1,1,1]],[1,"mofa2",false,1,[[0,-61,[18],19]],[5,768,791],[-11.489,-69.835,0,0,0,0,1,1,1,1]],[19,"New Particle",false,1,[[33,1,true,200,200,0.8,0.5,0,7,2,12,2,-47.369998931884766,-47.369998931884766,-142.11000061035156,1,1000,100,-92.11000061035156,65.79000091552734,-671.0499877929688,65.79000091552734,-62,[20],[4,2750056959],[4,3337279231],[4,3607061206],[4,3170462648],[0,7,7],[0,0.25,0.8600000143051147],21]],[169.479,188.666,0,0,0,0.9325854855166049,-0.3609491823009968,1,1,1],[1,0,0,222.317]],[2,"nvshenhei",3,[[0,-63,[22],23]],[5,384,314],[180.341,153.112,0,0,0,0,1,1,1,1]],[2,"mofa3",3,[[0,-64,[24],25]],[5,604,793],[-93.82,-161.651,0,0,0,0,1,1,1,1]],[1,"boyD2",false,3,[[0,-65,[26],27]],[5,362,437],[-218.71,-168.311,0,0,0,0,1,1,1,1]],[1,"boyD1",false,3,[[0,-66,[28],29]],[5,400,402],[-198.281,-145.054,0,0,0,0,1,1,1,1]],[2,"boyD3",3,[[0,-67,[30],31]],[5,365,453],[-217.414,-176.729,0,0,0,0,1,1,1,1]],[2,"speedline1",3,[[0,-68,[32],33]],[5,461,499],[-194.278,-162.255,0,0,0,0,1,1,1,1]],[2,"speedline2",3,[[0,-69,[34],35]],[5,535,558],[-195.346,-176.132,0,0,0,0,1,1,1,1]],[2,"mofa4",3,[[0,-70,[36],37]],[5,585,727],[-100.124,-108.703,0,0,0,0,1,1,1,1]],[6,"New Particle",3,[[34,true,200,200,0.8,0.5,0,70,20,20,20,30,-47.369998931884766,-47.369998931884766,-142.11000061035156,1,650,100,-92.11000061035156,65.79000091552734,-671.0499877929688,65.79000091552734,-71,[38],[4,2735343371],[4,3322085892],[4,3590324224],[4,3154116608],[0,7,7],[0,0.25,0.8600000143051147],39]],[-186.154,-105.067,0,0,0,-0.9478630054222308,0.31867808671437703,1,1,1],[1,0,0,577.166]],[6,"New Particle",3,[[35,true,200,200,0.8,0.5,0,8,6,10,2,-47.369998931884766,-47.369998931884766,-142.11000061035156,1,1000,100,-92.11000061035156,65.79000091552734,-671.0499877929688,65.79000091552734,-72,[40],[4,2735343371],[4,3322085892],[4,3590324224],[4,3154116608],[0,7,7],[0,0.25,0.8600000143051147],41]],[166.913,190.179,0,0,0,0.9325854855166049,-0.3609491823009968,1,1,1],[1,0,0,222.317]],[20,"blue Particle",false,1,[[36,1,true,100,999.999985098839,0.3,360,360,15.3699999,20,20.3199997,10,-47.369998931884766,-47.369998931884766,-142.11000061035156,1,450,190.7899932861328,-92.11000061035156,65.79000091552734,-671.0499877929688,65.79000091552734,-73,[44],[4,2750845502],[4,3321888768],[4,3601675539],[4,3155036164],[0,7,7],[0,0.25,0.8600000143051147],45]],[-160.935,-167.126,0,0,0,0,1,1,1,1]],[1,"boym3",false,1,[[0,-74,[46],47]],[5,365,453],[-217.245,-176.44,0,0,0,0,1,1,1,1]],[1,"boym4",false,1,[[0,-75,[48],49]],[5,476,418],[-148.379,-147.002,0,0,0,0,1,1,1,1]],[1,"mofaParticle",false,1,[[0,-76,[50],51]],[5,484,449],[-155.85,-104.611,0,0,0,0,1,0.904,0.912,1]],[5,"end3Cbackground",4,[[0,-77,[53],54]],[5,716,285]],[2,"boym5_eye",8,[[0,-78,[55],56]],[5,175,38],[0,15.307,0,0,0,0,1,1,1,1]],[21,"handjoit",4,[-79]],[2,"boym5_hand",40,[[0,-80,[59],60]],[5,633,224],[0,-146.181,0,0,0,0,1,1,1,1]],[22,"talk",2,[-1.523,-51.794,0,0,0,0,1,2.1,2.1,1]]],0,[0,0,1,0,-1,16,0,-2,17,0,-3,18,0,-4,19,0,-5,20,0,-6,21,0,-7,22,0,-8,23,0,-9,3,0,-10,34,0,-11,35,0,-12,36,0,-13,37,0,4,42,0,5,12,0,6,14,0,7,13,0,0,2,0,0,2,0,0,2,0,-1,10,0,-2,11,0,-3,7,0,-4,14,0,-5,15,0,-7,4,0,-8,42,0,0,3,0,-1,24,0,-2,25,0,-3,26,0,-4,27,0,-5,28,0,-6,29,0,-7,30,0,-8,31,0,-9,32,0,-10,33,0,0,4,0,-1,38,0,-2,8,0,-3,40,0,0,5,0,0,5,0,-1,6,0,0,6,0,-1,13,0,0,7,0,0,8,0,-1,39,0,0,10,0,-1,12,0,0,15,0,0,16,0,0,17,0,0,18,0,0,19,0,0,20,0,0,21,0,0,22,0,0,23,0,0,24,0,0,25,0,0,26,0,0,27,0,0,28,0,0,29,0,0,30,0,0,31,0,0,32,0,0,33,0,0,34,0,0,35,0,0,36,0,0,37,0,0,38,0,0,39,0,-1,41,0,0,41,0,8,9,1,3,2,2,3,6,5,3,9,80],[0,0,0,0,0,0,0,0,0,0,0,0,0,0,0,0,0,0,0,0,0,0,0,0,0,0,0,0,0,0,0,0,0,0,0,0,0,0,0,0,0,0,0,0,0,0,0,0,0,0,0,0,0,0,0,0,0,0,0,0,0,0,0,0,0,0,0,0,0,0,0,12,13],[-1,1,-1,-1,-1,1,-1,1,-1,1,-1,1,-1,1,-1,1,-1,1,-1,1,-1,1,-1,1,-1,1,-1,1,-1,1,-1,1,-1,1,-1,1,-1,1,-1,1,-1,1,-1,1,-1,1,-1,1,-1,1,-1,1,-1,-1,1,-1,1,-1,1,-1,1,-1,9,10,-1,-2,-3,-4,-5,-6,11,1,1],[0,4,0,0,0,5,0,6,0,7,0,8,0,9,0,10,0,11,0,12,0,13,0,14,0,15,0,16,0,17,0,18,0,19,0,20,0,21,0,1,0,1,0,22,0,23,0,24,0,25,0,26,0,0,27,0,28,0,29,0,30,0,31,2,2,32,33,34,35,36,37,38,39]],[[[3,"badend1",17.8,30,[{"frame":17.8,"func":"endClipTwo","params":[]}],{"paths":{"End1Cbackground":{"props":{"active":[{"frame":0,"value":true},{"frame":0.1,"value":true},{"frame":17.766666666666666,"value":true},{"frame":17.8,"value":false}],"opacity":[{"frame":0,"value":0},{"frame":0.7333333333333333,"value":255},{"frame":17,"value":255},{"frame":17.766666666666666,"value":0}]}},"End1Cbackground/nvshen":{"props":{"position":[{"frame":0.6666666666666666,"value":[184.933,448.25600000000065,0]},{"frame":1.3,"value":[184.933,153.112,0]},{"frame":12.566666666666666,"value":[184.933,153.112,0]},{"frame":13.266666666666667,"value":[184.933,449.366,0]}]}},"End1Cbackground/mofa1":{"props":{"active":[{"frame":1.8666666666666667,"value":false},{"frame":1.9,"value":true},{"frame":2.033333333333333,"value":true},{"frame":2.066666666666667,"value":false}],"opacity":[{"frame":1.9,"value":0},{"frame":1.9666666666666666,"value":255}]}},"End1Cbackground/boym1glow":{"props":{"active":[{"frame":2,"value":false},{"frame":2.033333333333333,"value":true},{"frame":3.066666666666667,"value":false}],"opacity":[{"frame":2.033333333333333,"value":0},{"frame":2.2333333333333334,"value":255}]}},"End1Cbackground/mofa2":{"props":{"active":[{"frame":2.033333333333333,"value":false},{"frame":2.066666666666667,"value":true},{"frame":9.7,"value":true},{"frame":9.733333333333333,"value":false}]}},"End1Cbackground/boym2":{"props":{"active":[{"frame":3.033333333333333,"value":false},{"frame":3.066666666666667,"value":true},{"frame":9.7,"value":true},{"frame":9.733333333333333,"value":false}]}},"End1Cbackground/boym1":{"props":{"active":[{"frame":3.033333333333333,"value":true},{"frame":3.066666666666667,"value":false}]}},"End1Cbackground/End2Cbackground":{"props":{"active":[{"frame":4.3,"value":false},{"frame":4.333333333333333,"value":true},{"frame":4.466666666666667,"value":true},{"frame":4.5,"value":false},{"frame":4.566666666666666,"value":false},{"frame":4.6,"value":true},{"frame":4.7,"value":true},{"frame":4.733333333333333,"value":false},{"frame":4.8,"value":false},{"frame":4.833333333333333,"value":true},{"frame":4.933333333333334,"value":true},{"frame":4.966666666666667,"value":false},{"frame":5.033333333333333,"value":false},{"frame":5.066666666666666,"value":true},{"frame":5.133333333333334,"value":true},{"frame":5.166666666666667,"value":false},{"frame":5.233333333333333,"value":false},{"frame":5.266666666666667,"value":true},{"frame":5.366666666666666,"value":true},{"frame":5.4,"value":false},{"frame":5.466666666666667,"value":false},{"frame":5.5,"value":true},{"frame":5.566666666666666,"value":true},{"frame":5.6,"value":false},{"frame":5.666666666666667,"value":false},{"frame":5.7,"value":true},{"frame":5.766666666666667,"value":true},{"frame":5.8,"value":false},{"frame":5.866666666666666,"value":false},{"frame":5.9,"value":true},{"frame":12.1,"value":true},{"frame":12.133333333333333,"value":false}],"opacity":[{"frame":4.333333333333333,"value":180},{"frame":5.966666666666667,"value":180},{"frame":6.166666666666667,"value":255},{"frame":12,"value":255},{"frame":12.133333333333333,"value":0}]}},"End1Cbackground/End2Cbackground/boyD2":{"props":{"active":[{"frame":7.966666666666667,"value":false},{"frame":8,"value":true},{"frame":10,"value":true},{"frame":10.033333333333333,"value":false}],"position":[{"frame":8,"value":[-218.7,-168.3],"motionPath":[]},{"frame":8.033333333333333,"value":[-222.677,-171.482,0]},{"frame":8.066666666666666,"value":[-218.632,-171.428,0]},{"frame":8.1,"value":[-221.02,-170.579,0]},{"frame":8.133333333333333,"value":[-224.161,-172.13,0]},{"frame":8.166666666666666,"value":[-221.677,-176.039,0]},{"frame":8.2,"value":[-217.645,-178.284,0]},{"frame":8.233333333333333,"value":[-222.677,-171.482,0]},{"frame":8.266666666666667,"value":[-218.632,-171.428,0]},{"frame":8.3,"value":[-221.02,-170.579,0]},{"frame":8.333333333333334,"value":[-224.161,-172.13,0]},{"frame":8.366666666666667,"value":[-221.677,-176.039,0]},{"frame":8.4,"value":[-217.645,-178.284,0]},{"frame":8.466666666666667,"value":[-222.677,-171.482,0]},{"frame":8.5,"value":[-218.632,-171.428,0]},{"frame":8.533333333333333,"value":[-221.02,-170.579,0]},{"frame":8.566666666666666,"value":[-224.161,-172.13,0]},{"frame":8.6,"value":[-221.677,-176.039,0]},{"frame":8.633333333333333,"value":[-217.645,-178.284,0]},{"frame":8.7,"value":[-222.677,-171.482,0]},{"frame":8.733333333333333,"value":[-218.632,-171.428,0]},{"frame":8.766666666666667,"value":[-221.02,-170.579,0]},{"frame":8.8,"value":[-224.161,-172.13,0]},{"frame":8.833333333333334,"value":[-221.677,-176.039,0]},{"frame":8.866666666666667,"value":[-217.645,-178.284,0]},{"frame":8.9,"value":[-222.677,-171.482,0]},{"frame":8.933333333333334,"value":[-218.632,-171.428,0]},{"frame":8.966666666666667,"value":[-221.02,-170.579,0]},{"frame":9,"value":[-224.161,-172.13,0]},{"frame":9.033333333333333,"value":[-221.677,-176.039,0]},{"frame":9.066666666666666,"value":[-217.645,-178.284,0]},{"frame":9.1,"value":[-222.677,-171.482,0]},{"frame":9.133333333333333,"value":[-218.632,-171.428,0]},{"frame":9.166666666666666,"value":[-221.02,-170.579,0]},{"frame":9.2,"value":[-224.161,-172.13,0]},{"frame":9.233333333333333,"value":[-221.677,-176.039,0]},{"frame":9.266666666666667,"value":[-217.645,-178.284,0]},{"frame":9.3,"value":[-222.677,-171.482,0]},{"frame":9.333333333333334,"value":[-218.632,-171.428,0]},{"frame":9.366666666666667,"value":[-221.02,-170.579,0]},{"frame":9.4,"value":[-224.161,-172.13,0]},{"frame":9.433333333333334,"value":[-221.677,-176.039,0]},{"frame":9.466666666666667,"value":[-217.645,-178.284,0]},{"frame":9.533333333333333,"value":[-222.677,-171.482,0]},{"frame":9.566666666666666,"value":[-218.632,-171.428,0]},{"frame":9.6,"value":[-221.02,-170.579,0]},{"frame":9.633333333333333,"value":[-224.161,-172.13,0]},{"frame":9.666666666666666,"value":[-221.677,-176.039,0]},{"frame":9.7,"value":[-217.645,-178.284,0]},{"frame":9.766666666666667,"value":[-222.677,-171.482,0]},{"frame":9.8,"value":[-218.632,-171.428,0]},{"frame":9.833333333333334,"value":[-221.02,-170.579,0]},{"frame":9.866666666666667,"value":[-224.161,-172.13,0]},{"frame":9.9,"value":[-221.677,-176.039,0]},{"frame":9.933333333333334,"value":[-217.645,-178.284,0]},{"frame":10,"value":[-218.7,-168.3],"motionPath":[]}]}},"End1Cbackground/End2Cbackground/boyD1":{"props":{"active":[{"frame":7.966666666666667,"value":true},{"frame":8,"value":false}],"position":[{"frame":6.133333333333334,"value":[-198.281,-145.054,0]},{"frame":6.166666666666667,"value":[-192.798,-148.709,0]},{"frame":6.2,"value":[-196.555,-144.986,0]},{"frame":6.233333333333333,"value":[-192.932,-144.987,0]},{"frame":6.266666666666667,"value":[-202.173,-144.988,0]},{"frame":6.3,"value":[-202.097,-144.989,0]},{"frame":6.333333333333333,"value":[-203.849,-148.645,0]},{"frame":6.366666666666666,"value":[-192.798,-148.709,0]},{"frame":6.4,"value":[-196.555,-144.986,0]},{"frame":6.433333333333334,"value":[-192.932,-144.987,0]},{"frame":6.466666666666667,"value":[-202.173,-144.988,0]},{"frame":6.5,"value":[-202.097,-144.989,0]},{"frame":6.533333333333333,"value":[-203.849,-148.645,0]},{"frame":6.566666666666666,"value":[-192.798,-148.709,0]},{"frame":6.6,"value":[-196.555,-144.986,0]},{"frame":6.633333333333334,"value":[-192.932,-144.987,0]},{"frame":6.666666666666667,"value":[-202.173,-144.988,0]},{"frame":6.7,"value":[-202.097,-144.989,0]},{"frame":6.733333333333333,"value":[-203.849,-148.645,0]},{"frame":6.766666666666667,"value":[-192.798,-148.709,0]},{"frame":6.8,"value":[-196.555,-144.986,0]},{"frame":6.833333333333333,"value":[-192.932,-144.987,0]},{"frame":6.866666666666666,"value":[-202.173,-144.988,0]},{"frame":6.9,"value":[-202.097,-144.989,0]},{"frame":6.933333333333334,"value":[-203.849,-148.645,0]},{"frame":6.966666666666667,"value":[-192.798,-148.709,0]},{"frame":7,"value":[-196.555,-144.986,0]},{"frame":7.033333333333333,"value":[-192.932,-144.987,0]},{"frame":7.066666666666666,"value":[-202.173,-144.988,0]},{"frame":7.1,"value":[-202.097,-144.989,0]},{"frame":7.133333333333334,"value":[-203.849,-148.645,0]},{"frame":7.166666666666667,"value":[-192.798,-148.709,0]},{"frame":7.2,"value":[-196.555,-144.986,0]},{"frame":7.233333333333333,"value":[-192.932,-144.987,0]},{"frame":7.266666666666667,"value":[-202.173,-144.988,0]},{"frame":7.3,"value":[-202.097,-144.989,0]},{"frame":7.333333333333333,"value":[-203.849,-148.645,0]},{"frame":7.366666666666666,"value":[-192.798,-148.709,0]},{"frame":7.4,"value":[-196.555,-144.986,0]},{"frame":7.433333333333334,"value":[-192.932,-144.987,0]},{"frame":7.466666666666667,"value":[-202.173,-144.988,0]},{"frame":7.5,"value":[-202.097,-144.989,0]},{"frame":7.533333333333333,"value":[-203.849,-148.645,0]},{"frame":7.566666666666666,"value":[-192.798,-148.709,0]},{"frame":7.6,"value":[-196.555,-144.986,0]},{"frame":7.633333333333334,"value":[-192.932,-144.987,0]},{"frame":7.666666666666667,"value":[-202.173,-144.988,0]},{"frame":7.7,"value":[-202.097,-144.989,0]},{"frame":7.733333333333333,"value":[-192.798,-148.709,0]},{"frame":7.766666666666667,"value":[-196.555,-144.986,0]},{"frame":7.8,"value":[-192.932,-144.987,0]},{"frame":7.833333333333333,"value":[-202.173,-144.988,0]},{"frame":7.866666666666666,"value":[-202.097,-144.989,0]},{"frame":7.9,"value":[-203.849,-148.645,0]},{"frame":7.966666666666667,"value":[-198.281,-145.054,0]}]}},"End1Cbackground/End2Cbackground/boyD3":{"props":{"active":[{"frame":10,"value":false},{"frame":10.033333333333333,"value":true}],"position":[{"frame":10.033333333333333,"value":[-217.414,-176.729,0]},{"frame":10.066666666666666,"value":[-217.414,-180.66,0]},{"frame":10.1,"value":[-212.173,-181.854,0]},{"frame":10.133333333333333,"value":[-220.194,-181.699,0]},{"frame":10.166666666666666,"value":[-214.866,-181.544,0]},{"frame":10.2,"value":[-220.189,-181.389,0]},{"frame":10.266666666666667,"value":[-217.414,-180.66,0]},{"frame":10.3,"value":[-212.173,-181.854,0]},{"frame":10.333333333333334,"value":[-220.194,-181.699,0]},{"frame":10.366666666666667,"value":[-214.866,-181.544,0]},{"frame":10.4,"value":[-220.189,-181.389,0]},{"frame":10.433333333333334,"value":[-217.414,-180.66,0]},{"frame":10.466666666666667,"value":[-212.173,-181.854,0]},{"frame":10.5,"value":[-220.194,-181.699,0]},{"frame":10.533333333333333,"value":[-214.866,-181.544,0]},{"frame":10.566666666666666,"value":[-220.189,-181.389,0]},{"frame":10.6,"value":[-217.414,-180.66,0]},{"frame":10.633333333333333,"value":[-212.173,-181.854,0]},{"frame":10.666666666666666,"value":[-220.194,-181.699,0]},{"frame":10.7,"value":[-214.866,-181.544,0]},{"frame":10.733333333333333,"value":[-220.189,-181.389,0]},{"frame":10.766666666666667,"value":[-217.414,-180.66,0]},{"frame":10.833333333333334,"value":[-212.173,-181.854,0]},{"frame":10.866666666666667,"value":[-220.194,-181.699,0]},{"frame":10.933333333333334,"value":[-214.866,-181.544,0]},{"frame":10.966666666666667,"value":[-220.189,-181.389,0]},{"frame":11,"value":[-217.414,-180.66,0]},{"frame":11.066666666666666,"value":[-212.173,-181.854,0]},{"frame":11.133333333333333,"value":[-220.194,-181.699,0]},{"frame":11.166666666666666,"value":[-214.866,-181.544,0]},{"frame":11.233333333333333,"value":[-220.189,-181.389,0]},{"frame":11.3,"value":[-217.414,-176.729,0]},{"frame":11.433333333333334,"value":[-213.483,-176.729,0]},{"frame":11.566666666666666,"value":[-218.724,-176.729,0]},{"frame":11.733333333333333,"value":[-212.172,-176.729,0]},{"frame":11.766666666666667,"value":[-217.413,-176.729,0]},{"frame":11.866666666666667,"value":[-212.172,-176.729,0]},{"frame":11.9,"value":[-213.482,-176.729,0]},{"frame":11.966666666666667,"value":[-217.413,-176.729,0]}]}},"End1Cbackground/boym3":{"props":{"active":[{"frame":11.866666666666667,"value":false},{"frame":11.9,"value":true},{"frame":14.6,"value":true},{"frame":14.633333333333333,"value":false}],"opacity":[{"frame":11.9,"value":0},{"frame":12.1,"value":255},{"frame":14.3,"value":255},{"frame":14.7,"value":0}]}},"End1Cbackground/boym4":{"props":{"active":[{"frame":14.4,"value":false},{"frame":14.433333333333334,"value":true}],"opacity":[{"frame":14.433333333333334,"value":0},{"frame":14.733333333333333,"value":255}]}},"End1Cbackground/New Particle":{"props":{"active":[{"frame":1.9666666666666666,"value":false},{"frame":2.066666666666667,"value":true},{"frame":6.066666666666666,"value":true},{"frame":6.1,"value":false}]}},"End1Cbackground/End2Cbackground/New Particle":{"props":{"active":[{"frame":6.1,"value":false},{"frame":6.133333333333334,"value":true}]}},"End1Cbackground/blue Particle":{"props":{"active":[{"frame":12,"value":false},{"frame":12.033333333333333,"value":true},{"frame":15.433333333333334,"value":true},{"frame":15.466666666666667,"value":false}]},"comps":{"cc.ParticleSystem":{"totalParticles":[{"frame":14.433333333333334,"value":100},{"frame":15.466666666666667,"value":0}]}}}}}]],0,0,[],[],[]],[[[9,"endlight",0.15,{"paths":{"lightEnd":{"props":{"opacity":[{"frame":0,"value":0},{"frame":0.15,"value":255}],"active":[{"frame":0,"value":true}]}}}}]],0,0,[],[],[]],[[{"name":"atom","rect":[0,0,31,31],"offset":[0,0],"originalSize":[31,31],"capInsets":[0,0,0,0]}],[1],0,[0],[2],[40]],[[{"name":"default_sprite_splash","rect":[0,0,2,2],"offset":[0,0],"originalSize":[2,2],"capInsets":[0,0,0,0]}],[1],0,[0],[2],[41]],[[{"name":"z1","rect":[171,1,32,32],"offset":[0,0],"originalSize":[32,32],"capInsets":[0,0,0,0]}],[1],0,[0],[2],[42]],[[[10,"badend2b",0.9166666666666666,[{"frame":0.9166666666666666,"func":"intofinaltalkThree","params":[]}],{"paths":{"end3Cbackground/handjoit/boym5_hand":{"props":{"position":[{"frame":0,"value":[-5.92,-146.95]}]}},"end3Cbackground":{"props":{"active":[{"frame":0,"value":true},{"frame":0.9,"value":true},{"frame":0.9166666666666666,"value":false}],"opacity":[{"frame":0,"value":255},{"frame":0.9,"value":0}]}},"end3Cbackground/handjoit":{"props":{"position":[{"frame":0,"value":[0,19.462,0]}]}}}}]],0,0,[],[],[]]]]